[{"Mode":"voltage-clamp","Erev":-7.48,"Vm":-91.23,"Rin":100.0,"Rin_min":10.0,"Rin_max":400.0,"Cm":100.0,"Cm_min":10.0,"Cm_max":400.0,"g_syn":17.732,"g_syn_min":0.01,"g_syn_max":30.0,"tau_d":7.663,"tau_d_min":0.3,"tau_d_max":30.0,"tau_f":4.439,"tau_f_min":1.0,"tau_f_max":30000.0,"tau_r":1039.203,"tau_r_min":1.0,"tau_r_max":30000.0,"U":0.17,"U_min":0.001,"U_max":0.999,"error":0.06287},{"Mode":"voltage-clamp","Erev":-7.48,"Vm":-91.23,"Rin":100.0,"Rin_min":10.0,"Rin_max":400.0,"Cm":100.0,"Cm_min":10.0,"Cm_max":400.0,"g_syn":17.803,"g_syn_min":0.01,"g_syn_max":30.0,"tau_d":7.615,"tau_d_min":0.3,"tau_d_max":30.0,"tau_f":8.871,"tau_f_min":1.0,"tau_f_max":30000.0,"tau_r":1047.632,"tau_r_min":1.0,"tau_r_max":30000.0,"U":0.17,"U_min":0.001,"U_max":0.999,"error":0.06286},{"Mode":"voltage-clamp","Erev":-7.48,"Vm":-91.23,"Rin":100.0,"Rin_min":10.0,"Rin_max":400.0,"Cm":100.0,"Cm_min":10.0,"Cm_max":400.0,"g_syn":17.711,"g_syn_min":0.01,"g_syn_max":30.0,"tau_d":7.63,"tau_d_min":0.3,"tau_d_max":30.0,"tau_f":8.683,"tau_f_min":1.0,"tau_f_max":30000.0,"tau_r":1030.548,"tau_r_min":1.0,"tau_r_max":30000.0,"U":0.171,"U_min":0.001,"U_max":0.999,"error":0.06286},{"Mode":"voltage-clamp","Erev":-7.48,"Vm":-91.23,"Rin":100.0,"Rin_min":10.0,"Rin_max":400.0,"Cm":100.0,"Cm_min":10.0,"Cm_max":400.0,"g_syn":17.719,"g_syn_min":0.01,"g_syn_max":30.0,"tau_d":7.58,"tau_d_min":0.3,"tau_d_max":30.0,"tau_f":1.855,"tau_f_min":1.0,"tau_f_max":30000.0,"tau_r":1031.169,"tau_r_min":1.0,"tau_r_max":30000.0,"U":0.17,"U_min":0.001,"U_max":0.999,"error":0.06286},{"Mode":"voltage-clamp","Erev":-7.48,"Vm":-91.23,"Rin":100.0,"Rin_min":10.0,"Rin_max":400.0,"Cm":100.0,"Cm_min":10.0,"Cm_max":400.0,"g_syn":17.741,"g_syn_min":0.01,"g_syn_max":30.0,"tau_d":7.639,"tau_d_min":0.3,"tau_d_max":30.0,"tau_f":2.909,"tau_f_min":1.0,"tau_f_max":30000.0,"tau_r":1036.36,"tau_r_min":1.0,"tau_r_max":30000.0,"U":0.17,"U_min":0.001,"U_max":0.999,"error":0.06285},{"Mode":"voltage-clamp","Erev":-7.48,"Vm":-91.23,"Rin":100.0,"Rin_min":10.0,"Rin_max":400.0,"Cm":100.0,"Cm_min":10.0,"Cm_max":400.0,"g_syn":17.7,"g_syn_min":0.01,"g_syn_max":30.0,"tau_d":7.591,"tau_d_min":0.3,"tau_d_max":30.0,"tau_f":1.844,"tau_f_min":1.0,"tau_f_max":30000.0,"tau_r":1032.79,"tau_r_min":1.0,"tau_r_max":30000.0,"U":0.171,"U_min":0.001,"U_max":0.999,"error":0.06286},{"Mode":"voltage-clamp","Erev":-7.48,"Vm":-91.23,"Rin":100.0,"Rin_min":10.0,"Rin_max":400.0,"Cm":100.0,"Cm_min":10.0,"Cm_max":400.0,"g_syn":17.767,"g_syn_min":0.01,"g_syn_max":30.0,"tau_d":7.602,"tau_d_min":0.3,"tau_d_max":30.0,"tau_f":6.52,"tau_f_min":1.0,"tau_f_max":30000.0,"tau_r":1041.259,"tau_r_min":1.0,"tau_r_max":30000.0,"U":0.17,"U_min":0.001,"U_max":0.999,"error":0.06286},{"Mode":"voltage-clamp","Erev":-7.48,"Vm":-91.23,"Rin":100.0,"Rin_min":10.0,"Rin_max":400.0,"Cm":100.0,"Cm_min":10.0,"Cm_max":400.0,"g_syn":17.765,"g_syn_min":0.01,"g_syn_max":30.0,"tau_d":7.644,"tau_d_min":0.3,"tau_d_max":30.0,"tau_f":7.091,"tau_f_min":1.0,"tau_f_max":30000.0,"tau_r":1040.241,"tau_r_min":1.0,"tau_r_max":30000.0,"U":0.17,"U_min":0.001,"U_max":0.999,"error":0.06285},{"Mode":"voltage-clamp","Erev":-7.48,"Vm":-91.23,"Rin":100.0,"Rin_min":10.0,"Rin_max":400.0,"Cm":100.0,"Cm_min":10.0,"Cm_max":400.0,"g_syn":17.686,"g_syn_min":0.01,"g_syn_max":30.0,"tau_d":7.641,"tau_d_min":0.3,"tau_d_max":30.0,"tau_f":3.947,"tau_f_min":1.0,"tau_f_max":30000.0,"tau_r":1025.151,"tau_r_min":1.0,"tau_r_max":30000.0,"U":0.171,"U_min":0.001,"U_max":0.999,"error":0.06286},{"Mode":"voltage-clamp","Erev":-7.48,"Vm":-91.23,"Rin":100.0,"Rin_min":10.0,"Rin_max":400.0,"Cm":100.0,"Cm_min":10.0,"Cm_max":400.0,"g_syn":17.724,"g_syn_min":0.01,"g_syn_max":30.0,"tau_d":7.631,"tau_d_min":0.3,"tau_d_max":30.0,"tau_f":8.1,"tau_f_min":1.0,"tau_f_max":30000.0,"tau_r":1032.202,"tau_r_min":1.0,"tau_r_max":30000.0,"U":0.17,"U_min":0.001,"U_max":0.999,"error":0.06285},{"Mode":"voltage-clamp","Erev":-7.48,"Vm":-91.23,"Rin":100.0,"Rin_min":10.0,"Rin_max":400.0,"Cm":100.0,"Cm_min":10.0,"Cm_max":400.0,"g_syn":17.701,"g_syn_min":0.01,"g_syn_max":30.0,"tau_d":7.591,"tau_d_min":0.3,"tau_d_max":30.0,"tau_f":10.108,"tau_f_min":1.0,"tau_f_max":30000.0,"tau_r":1031.936,"tau_r_min":1.0,"tau_r_max":30000.0,"U":0.171,"U_min":0.001,"U_max":0.999,"error":0.06286},{"Mode":"voltage-clamp","Erev":-7.48,"Vm":-91.23,"Rin":100.0,"Rin_min":10.0,"Rin_max":400.0,"Cm":100.0,"Cm_min":10.0,"Cm_max":400.0,"g_syn":17.746,"g_syn_min":0.01,"g_syn_max":30.0,"tau_d":7.601,"tau_d_min":0.3,"tau_d_max":30.0,"tau_f":3.942,"tau_f_min":1.0,"tau_f_max":30000.0,"tau_r":1033.484,"tau_r_min":1.0,"tau_r_max":30000.0,"U":0.17,"U_min":0.001,"U_max":0.999,"error":0.06286},{"Mode":"voltage-clamp","Erev":-7.48,"Vm":-91.23,"Rin":100.0,"Rin_min":10.0,"Rin_max":400.0,"Cm":100.0,"Cm_min":10.0,"Cm_max":400.0,"g_syn":17.699,"g_syn_min":0.01,"g_syn_max":30.0,"tau_d":7.601,"tau_d_min":0.3,"tau_d_max":30.0,"tau_f":6.411,"tau_f_min":1.0,"tau_f_max":30000.0,"tau_r":1032.742,"tau_r_min":1.0,"tau_r_max":30000.0,"U":0.171,"U_min":0.001,"U_max":0.999,"error":0.06286},{"Mode":"voltage-clamp","Erev":-7.48,"Vm":-91.23,"Rin":100.0,"Rin_min":10.0,"Rin_max":400.0,"Cm":100.0,"Cm_min":10.0,"Cm_max":400.0,"g_syn":17.785,"g_syn_min":0.01,"g_syn_max":30.0,"tau_d":7.633,"tau_d_min":0.3,"tau_d_max":30.0,"tau_f":5.229,"tau_f_min":1.0,"tau_f_max":30000.0,"tau_r":1040.5,"tau_r_min":1.0,"tau_r_max":30000.0,"U":0.17,"U_min":0.001,"U_max":0.999,"error":0.06285},{"Mode":"voltage-clamp","Erev":-7.48,"Vm":-91.23,"Rin":100.0,"Rin_min":10.0,"Rin_max":400.0,"Cm":100.0,"Cm_min":10.0,"Cm_max":400.0,"g_syn":17.725,"g_syn_min":0.01,"g_syn_max":30.0,"tau_d":7.621,"tau_d_min":0.3,"tau_d_max":30.0,"tau_f":3.113,"tau_f_min":1.0,"tau_f_max":30000.0,"tau_r":1033.419,"tau_r_min":1.0,"tau_r_max":30000.0,"U":0.17,"U_min":0.001,"U_max":0.999,"error":0.06285},{"Mode":"voltage-clamp","Erev":-7.48,"Vm":-91.23,"Rin":100.0,"Rin_min":10.0,"Rin_max":400.0,"Cm":100.0,"Cm_min":10.0,"Cm_max":400.0,"g_syn":17.726,"g_syn_min":0.01,"g_syn_max":30.0,"tau_d":7.645,"tau_d_min":0.3,"tau_d_max":30.0,"tau_f":8.089,"tau_f_min":1.0,"tau_f_max":30000.0,"tau_r":1033.018,"tau_r_min":1.0,"tau_r_max":30000.0,"U":0.17,"U_min":0.001,"U_max":0.999,"error":0.06286},{"Mode":"voltage-clamp","Erev":-7.48,"Vm":-91.23,"Rin":100.0,"Rin_min":10.0,"Rin_max":400.0,"Cm":100.0,"Cm_min":10.0,"Cm_max":400.0,"g_syn":17.667,"g_syn_min":0.01,"g_syn_max":30.0,"tau_d":7.611,"tau_d_min":0.3,"tau_d_max":30.0,"tau_f":5.406,"tau_f_min":1.0,"tau_f_max":30000.0,"tau_r":1023.905,"tau_r_min":1.0,"tau_r_max":30000.0,"U":0.171,"U_min":0.001,"U_max":0.999,"error":0.06286},{"Mode":"voltage-clamp","Erev":-7.48,"Vm":-91.23,"Rin":100.0,"Rin_min":10.0,"Rin_max":400.0,"Cm":100.0,"Cm_min":10.0,"Cm_max":400.0,"g_syn":17.76,"g_syn_min":0.01,"g_syn_max":30.0,"tau_d":7.635,"tau_d_min":0.3,"tau_d_max":30.0,"tau_f":9.263,"tau_f_min":1.0,"tau_f_max":30000.0,"tau_r":1041.226,"tau_r_min":1.0,"tau_r_max":30000.0,"U":0.17,"U_min":0.001,"U_max":0.999,"error":0.06286},{"Mode":"voltage-clamp","Erev":-7.48,"Vm":-91.23,"Rin":100.0,"Rin_min":10.0,"Rin_max":400.0,"Cm":100.0,"Cm_min":10.0,"Cm_max":400.0,"g_syn":17.725,"g_syn_min":0.01,"g_syn_max":30.0,"tau_d":7.636,"tau_d_min":0.3,"tau_d_max":30.0,"tau_f":5.642,"tau_f_min":1.0,"tau_f_max":30000.0,"tau_r":1034.088,"tau_r_min":1.0,"tau_r_max":30000.0,"U":0.17,"U_min":0.001,"U_max":0.999,"error":0.06285},{"Mode":"voltage-clamp","Erev":-7.48,"Vm":-91.23,"Rin":100.0,"Rin_min":10.0,"Rin_max":400.0,"Cm":100.0,"Cm_min":10.0,"Cm_max":400.0,"g_syn":17.736,"g_syn_min":0.01,"g_syn_max":30.0,"tau_d":7.624,"tau_d_min":0.3,"tau_d_max":30.0,"tau_f":6.721,"tau_f_min":1.0,"tau_f_max":30000.0,"tau_r":1034.894,"tau_r_min":1.0,"tau_r_max":30000.0,"U":0.17,"U_min":0.001,"U_max":0.999,"error":0.06285},{"Mode":"voltage-clamp","Erev":-7.48,"Vm":-91.23,"Rin":100.0,"Rin_min":10.0,"Rin_max":400.0,"Cm":100.0,"Cm_min":10.0,"Cm_max":400.0,"g_syn":17.718,"g_syn_min":0.01,"g_syn_max":30.0,"tau_d":7.6,"tau_d_min":0.3,"tau_d_max":30.0,"tau_f":4.104,"tau_f_min":1.0,"tau_f_max":30000.0,"tau_r":1035.23,"tau_r_min":1.0,"tau_r_max":30000.0,"U":0.171,"U_min":0.001,"U_max":0.999,"error":0.06286},{"Mode":"voltage-clamp","Erev":-7.48,"Vm":-91.23,"Rin":100.0,"Rin_min":10.0,"Rin_max":400.0,"Cm":100.0,"Cm_min":10.0,"Cm_max":400.0,"g_syn":17.745,"g_syn_min":0.01,"g_syn_max":30.0,"tau_d":7.659,"tau_d_min":0.3,"tau_d_max":30.0,"tau_f":5.747,"tau_f_min":1.0,"tau_f_max":30000.0,"tau_r":1032.322,"tau_r_min":1.0,"tau_r_max":30000.0,"U":0.17,"U_min":0.001,"U_max":0.999,"error":0.06287},{"Mode":"voltage-clamp","Erev":-7.48,"Vm":-91.23,"Rin":100.0,"Rin_min":10.0,"Rin_max":400.0,"Cm":100.0,"Cm_min":10.0,"Cm_max":400.0,"g_syn":17.747,"g_syn_min":0.01,"g_syn_max":30.0,"tau_d":7.647,"tau_d_min":0.3,"tau_d_max":30.0,"tau_f":7.03,"tau_f_min":1.0,"tau_f_max":30000.0,"tau_r":1038.41,"tau_r_min":1.0,"tau_r_max":30000.0,"U":0.17,"U_min":0.001,"U_max":0.999,"error":0.06286},{"Mode":"voltage-clamp","Erev":-7.48,"Vm":-91.23,"Rin":100.0,"Rin_min":10.0,"Rin_max":400.0,"Cm":100.0,"Cm_min":10.0,"Cm_max":400.0,"g_syn":17.736,"g_syn_min":0.01,"g_syn_max":30.0,"tau_d":7.606,"tau_d_min":0.3,"tau_d_max":30.0,"tau_f":5.297,"tau_f_min":1.0,"tau_f_max":30000.0,"tau_r":1035.64,"tau_r_min":1.0,"tau_r_max":30000.0,"U":0.17,"U_min":0.001,"U_max":0.999,"error":0.06285},{"Mode":"voltage-clamp","Erev":-7.48,"Vm":-91.23,"Rin":100.0,"Rin_min":10.0,"Rin_max":400.0,"Cm":100.0,"Cm_min":10.0,"Cm_max":400.0,"g_syn":17.714,"g_syn_min":0.01,"g_syn_max":30.0,"tau_d":7.601,"tau_d_min":0.3,"tau_d_max":30.0,"tau_f":4.888,"tau_f_min":1.0,"tau_f_max":30000.0,"tau_r":1033.67,"tau_r_min":1.0,"tau_r_max":30000.0,"U":0.171,"U_min":0.001,"U_max":0.999,"error":0.06286},{"Mode":"voltage-clamp","Erev":-7.48,"Vm":-91.23,"Rin":100.0,"Rin_min":10.0,"Rin_max":400.0,"Cm":100.0,"Cm_min":10.0,"Cm_max":400.0,"g_syn":17.762,"g_syn_min":0.01,"g_syn_max":30.0,"tau_d":7.61,"tau_d_min":0.3,"tau_d_max":30.0,"tau_f":1.913,"tau_f_min":1.0,"tau_f_max":30000.0,"tau_r":1038.534,"tau_r_min":1.0,"tau_r_max":30000.0,"U":0.17,"U_min":0.001,"U_max":0.999,"error":0.06285},{"Mode":"voltage-clamp","Erev":-7.48,"Vm":-91.23,"Rin":100.0,"Rin_min":10.0,"Rin_max":400.0,"Cm":100.0,"Cm_min":10.0,"Cm_max":400.0,"g_syn":17.699,"g_syn_min":0.01,"g_syn_max":30.0,"tau_d":7.605,"tau_d_min":0.3,"tau_d_max":30.0,"tau_f":8.248,"tau_f_min":1.0,"tau_f_max":30000.0,"tau_r":1030.811,"tau_r_min":1.0,"tau_r_max":30000.0,"U":0.171,"U_min":0.001,"U_max":0.999,"error":0.06286},{"Mode":"voltage-clamp","Erev":-7.48,"Vm":-91.23,"Rin":100.0,"Rin_min":10.0,"Rin_max":400.0,"Cm":100.0,"Cm_min":10.0,"Cm_max":400.0,"g_syn":17.742,"g_syn_min":0.01,"g_syn_max":30.0,"tau_d":7.624,"tau_d_min":0.3,"tau_d_max":30.0,"tau_f":3.496,"tau_f_min":1.0,"tau_f_max":30000.0,"tau_r":1035.179,"tau_r_min":1.0,"tau_r_max":30000.0,"U":0.17,"U_min":0.001,"U_max":0.999,"error":0.06285},{"Mode":"voltage-clamp","Erev":-7.48,"Vm":-91.23,"Rin":100.0,"Rin_min":10.0,"Rin_max":400.0,"Cm":100.0,"Cm_min":10.0,"Cm_max":400.0,"g_syn":17.672,"g_syn_min":0.01,"g_syn_max":30.0,"tau_d":7.62,"tau_d_min":0.3,"tau_d_max":30.0,"tau_f":11.286,"tau_f_min":1.0,"tau_f_max":30000.0,"tau_r":1026.279,"tau_r_min":1.0,"tau_r_max":30000.0,"U":0.171,"U_min":0.001,"U_max":0.999,"error":0.06286},{"Mode":"voltage-clamp","Erev":-7.48,"Vm":-91.23,"Rin":100.0,"Rin_min":10.0,"Rin_max":400.0,"Cm":100.0,"Cm_min":10.0,"Cm_max":400.0,"g_syn":17.739,"g_syn_min":0.01,"g_syn_max":30.0,"tau_d":7.596,"tau_d_min":0.3,"tau_d_max":30.0,"tau_f":5.547,"tau_f_min":1.0,"tau_f_max":30000.0,"tau_r":1036.37,"tau_r_min":1.0,"tau_r_max":30000.0,"U":0.17,"U_min":0.001,"U_max":0.999,"error":0.06286}]