[{"Mode":"voltage-clamp","Erev":-8.35,"Vm":-75.9,"Rin":100.0,"Rin_min":10.0,"Rin_max":400.0,"Cm":100.0,"Cm_min":10.0,"Cm_max":400.0,"g_syn":8.843,"g_syn_min":0.01,"g_syn_max":30.0,"tau_d":23.02,"tau_d_min":0.3,"tau_d_max":23.02,"tau_r":48.801,"tau_r_min":1.0,"tau_r_max":30000.0,"tau_f":6.209,"tau_f_min":1.0,"tau_f_max":30000.0,"U":0.095,"U_min":0.001,"U_max":0.999,"error":0.661,"isCmOptimized":false,"isRinOptimized":false},{"Mode":"voltage-clamp","Erev":-8.35,"Vm":-75.9,"Rin":100.0,"Rin_min":10.0,"Rin_max":400.0,"Cm":100.0,"Cm_min":10.0,"Cm_max":400.0,"g_syn":7.867,"g_syn_min":0.01,"g_syn_max":30.0,"tau_d":23.02,"tau_d_min":0.3,"tau_d_max":23.02,"tau_r":43.401,"tau_r_min":1.0,"tau_r_max":30000.0,"tau_f":6.766,"tau_f_min":1.0,"tau_f_max":30000.0,"U":0.107,"U_min":0.001,"U_max":0.999,"error":0.661,"isCmOptimized":false,"isRinOptimized":false},{"Mode":"voltage-clamp","Erev":-8.35,"Vm":-75.9,"Rin":100.0,"Rin_min":10.0,"Rin_max":400.0,"Cm":100.0,"Cm_min":10.0,"Cm_max":400.0,"g_syn":8.286,"g_syn_min":0.01,"g_syn_max":30.0,"tau_d":23.02,"tau_d_min":0.3,"tau_d_max":23.02,"tau_r":45.406,"tau_r_min":1.0,"tau_r_max":30000.0,"tau_f":6.405,"tau_f_min":1.0,"tau_f_max":30000.0,"U":0.101,"U_min":0.001,"U_max":0.999,"error":0.661,"isCmOptimized":false,"isRinOptimized":false},{"Mode":"voltage-clamp","Erev":-8.35,"Vm":-75.9,"Rin":100.0,"Rin_min":10.0,"Rin_max":400.0,"Cm":100.0,"Cm_min":10.0,"Cm_max":400.0,"g_syn":8.041,"g_syn_min":0.01,"g_syn_max":30.0,"tau_d":23.02,"tau_d_min":0.3,"tau_d_max":23.02,"tau_r":45.915,"tau_r_min":1.0,"tau_r_max":30000.0,"tau_f":6.657,"tau_f_min":1.0,"tau_f_max":30000.0,"U":0.105,"U_min":0.001,"U_max":0.999,"error":0.661,"isCmOptimized":false,"isRinOptimized":false},{"Mode":"voltage-clamp","Erev":-8.35,"Vm":-75.9,"Rin":100.0,"Rin_min":10.0,"Rin_max":400.0,"Cm":100.0,"Cm_min":10.0,"Cm_max":400.0,"g_syn":9.2,"g_syn_min":0.01,"g_syn_max":30.0,"tau_d":23.02,"tau_d_min":0.3,"tau_d_max":23.02,"tau_r":50.327,"tau_r_min":1.0,"tau_r_max":30000.0,"tau_f":6.008,"tau_f_min":1.0,"tau_f_max":30000.0,"U":0.091,"U_min":0.001,"U_max":0.999,"error":0.661,"isCmOptimized":false,"isRinOptimized":false},{"Mode":"voltage-clamp","Erev":-8.35,"Vm":-75.9,"Rin":100.0,"Rin_min":10.0,"Rin_max":400.0,"Cm":100.0,"Cm_min":10.0,"Cm_max":400.0,"g_syn":8.395,"g_syn_min":0.01,"g_syn_max":30.0,"tau_d":23.02,"tau_d_min":0.3,"tau_d_max":23.02,"tau_r":46.843,"tau_r_min":1.0,"tau_r_max":30000.0,"tau_f":6.31,"tau_f_min":1.0,"tau_f_max":30000.0,"U":0.101,"U_min":0.001,"U_max":0.999,"error":0.661,"isCmOptimized":false,"isRinOptimized":false},{"Mode":"voltage-clamp","Erev":-8.35,"Vm":-75.9,"Rin":100.0,"Rin_min":10.0,"Rin_max":400.0,"Cm":100.0,"Cm_min":10.0,"Cm_max":400.0,"g_syn":8.533,"g_syn_min":0.01,"g_syn_max":30.0,"tau_d":23.02,"tau_d_min":0.3,"tau_d_max":23.02,"tau_r":46.411,"tau_r_min":1.0,"tau_r_max":30000.0,"tau_f":6.203,"tau_f_min":1.0,"tau_f_max":30000.0,"U":0.099,"U_min":0.001,"U_max":0.999,"error":0.661,"isCmOptimized":false,"isRinOptimized":false},{"Mode":"voltage-clamp","Erev":-8.35,"Vm":-75.9,"Rin":100.0,"Rin_min":10.0,"Rin_max":400.0,"Cm":100.0,"Cm_min":10.0,"Cm_max":400.0,"g_syn":8.362,"g_syn_min":0.01,"g_syn_max":30.0,"tau_d":23.02,"tau_d_min":0.3,"tau_d_max":23.02,"tau_r":46.19,"tau_r_min":1.0,"tau_r_max":30000.0,"tau_f":6.443,"tau_f_min":1.0,"tau_f_max":30000.0,"U":0.101,"U_min":0.001,"U_max":0.999,"error":0.661,"isCmOptimized":false,"isRinOptimized":false},{"Mode":"voltage-clamp","Erev":-8.35,"Vm":-75.9,"Rin":100.0,"Rin_min":10.0,"Rin_max":400.0,"Cm":100.0,"Cm_min":10.0,"Cm_max":400.0,"g_syn":8.47,"g_syn_min":0.01,"g_syn_max":30.0,"tau_d":23.02,"tau_d_min":0.3,"tau_d_max":23.02,"tau_r":47.533,"tau_r_min":1.0,"tau_r_max":30000.0,"tau_f":6.54,"tau_f_min":1.0,"tau_f_max":30000.0,"U":0.099,"U_min":0.001,"U_max":0.999,"error":0.661,"isCmOptimized":false,"isRinOptimized":false},{"Mode":"voltage-clamp","Erev":-8.35,"Vm":-75.9,"Rin":100.0,"Rin_min":10.0,"Rin_max":400.0,"Cm":100.0,"Cm_min":10.0,"Cm_max":400.0,"g_syn":8.124,"g_syn_min":0.01,"g_syn_max":30.0,"tau_d":23.02,"tau_d_min":0.3,"tau_d_max":23.02,"tau_r":45.24,"tau_r_min":1.0,"tau_r_max":30000.0,"tau_f":6.64,"tau_f_min":1.0,"tau_f_max":30000.0,"U":0.103,"U_min":0.001,"U_max":0.999,"error":0.661,"isCmOptimized":false,"isRinOptimized":false},{"Mode":"voltage-clamp","Erev":-8.35,"Vm":-75.9,"Rin":100.0,"Rin_min":10.0,"Rin_max":400.0,"Cm":100.0,"Cm_min":10.0,"Cm_max":400.0,"g_syn":7.77,"g_syn_min":0.01,"g_syn_max":30.0,"tau_d":23.02,"tau_d_min":0.3,"tau_d_max":23.02,"tau_r":43.93,"tau_r_min":1.0,"tau_r_max":30000.0,"tau_f":7.062,"tau_f_min":1.0,"tau_f_max":30000.0,"U":0.108,"U_min":0.001,"U_max":0.999,"error":0.661,"isCmOptimized":false,"isRinOptimized":false},{"Mode":"voltage-clamp","Erev":-8.35,"Vm":-75.9,"Rin":100.0,"Rin_min":10.0,"Rin_max":400.0,"Cm":100.0,"Cm_min":10.0,"Cm_max":400.0,"g_syn":8.149,"g_syn_min":0.01,"g_syn_max":30.0,"tau_d":23.02,"tau_d_min":0.3,"tau_d_max":23.02,"tau_r":46.401,"tau_r_min":1.0,"tau_r_max":30000.0,"tau_f":6.688,"tau_f_min":1.0,"tau_f_max":30000.0,"U":0.103,"U_min":0.001,"U_max":0.999,"error":0.661,"isCmOptimized":false,"isRinOptimized":false},{"Mode":"voltage-clamp","Erev":-8.35,"Vm":-75.9,"Rin":100.0,"Rin_min":10.0,"Rin_max":400.0,"Cm":100.0,"Cm_min":10.0,"Cm_max":400.0,"g_syn":8.763,"g_syn_min":0.01,"g_syn_max":30.0,"tau_d":23.02,"tau_d_min":0.3,"tau_d_max":23.02,"tau_r":48.734,"tau_r_min":1.0,"tau_r_max":30000.0,"tau_f":6.28,"tau_f_min":1.0,"tau_f_max":30000.0,"U":0.096,"U_min":0.001,"U_max":0.999,"error":0.661,"isCmOptimized":false,"isRinOptimized":false},{"Mode":"voltage-clamp","Erev":-8.35,"Vm":-75.9,"Rin":100.0,"Rin_min":10.0,"Rin_max":400.0,"Cm":100.0,"Cm_min":10.0,"Cm_max":400.0,"g_syn":9.247,"g_syn_min":0.01,"g_syn_max":30.0,"tau_d":23.02,"tau_d_min":0.3,"tau_d_max":23.02,"tau_r":51.572,"tau_r_min":1.0,"tau_r_max":30000.0,"tau_f":5.861,"tau_f_min":1.0,"tau_f_max":30000.0,"U":0.091,"U_min":0.001,"U_max":0.999,"error":0.661,"isCmOptimized":false,"isRinOptimized":false},{"Mode":"voltage-clamp","Erev":-8.35,"Vm":-75.9,"Rin":100.0,"Rin_min":10.0,"Rin_max":400.0,"Cm":100.0,"Cm_min":10.0,"Cm_max":400.0,"g_syn":7.483,"g_syn_min":0.01,"g_syn_max":30.0,"tau_d":23.02,"tau_d_min":0.3,"tau_d_max":23.02,"tau_r":41.885,"tau_r_min":1.0,"tau_r_max":30000.0,"tau_f":7.065,"tau_f_min":1.0,"tau_f_max":30000.0,"U":0.112,"U_min":0.001,"U_max":0.999,"error":0.661,"isCmOptimized":false,"isRinOptimized":false},{"Mode":"voltage-clamp","Erev":-8.35,"Vm":-75.9,"Rin":100.0,"Rin_min":10.0,"Rin_max":400.0,"Cm":100.0,"Cm_min":10.0,"Cm_max":400.0,"g_syn":8.929,"g_syn_min":0.01,"g_syn_max":30.0,"tau_d":23.02,"tau_d_min":0.3,"tau_d_max":23.02,"tau_r":49.625,"tau_r_min":1.0,"tau_r_max":30000.0,"tau_f":6.232,"tau_f_min":1.0,"tau_f_max":30000.0,"U":0.094,"U_min":0.001,"U_max":0.999,"error":0.661,"isCmOptimized":false,"isRinOptimized":false},{"Mode":"voltage-clamp","Erev":-8.35,"Vm":-75.9,"Rin":100.0,"Rin_min":10.0,"Rin_max":400.0,"Cm":100.0,"Cm_min":10.0,"Cm_max":400.0,"g_syn":9.0,"g_syn_min":0.01,"g_syn_max":30.0,"tau_d":23.02,"tau_d_min":0.3,"tau_d_max":23.02,"tau_r":49.804,"tau_r_min":1.0,"tau_r_max":30000.0,"tau_f":6.166,"tau_f_min":1.0,"tau_f_max":30000.0,"U":0.093,"U_min":0.001,"U_max":0.999,"error":0.661,"isCmOptimized":false,"isRinOptimized":false},{"Mode":"voltage-clamp","Erev":-8.35,"Vm":-75.9,"Rin":100.0,"Rin_min":10.0,"Rin_max":400.0,"Cm":100.0,"Cm_min":10.0,"Cm_max":400.0,"g_syn":8.016,"g_syn_min":0.01,"g_syn_max":30.0,"tau_d":23.02,"tau_d_min":0.3,"tau_d_max":23.02,"tau_r":44.816,"tau_r_min":1.0,"tau_r_max":30000.0,"tau_f":6.75,"tau_f_min":1.0,"tau_f_max":30000.0,"U":0.105,"U_min":0.001,"U_max":0.999,"error":0.661,"isCmOptimized":false,"isRinOptimized":false},{"Mode":"voltage-clamp","Erev":-8.35,"Vm":-75.9,"Rin":100.0,"Rin_min":10.0,"Rin_max":400.0,"Cm":100.0,"Cm_min":10.0,"Cm_max":400.0,"g_syn":8.341,"g_syn_min":0.01,"g_syn_max":30.0,"tau_d":23.02,"tau_d_min":0.3,"tau_d_max":23.02,"tau_r":45.955,"tau_r_min":1.0,"tau_r_max":30000.0,"tau_f":6.463,"tau_f_min":1.0,"tau_f_max":30000.0,"U":0.101,"U_min":0.001,"U_max":0.999,"error":0.661,"isCmOptimized":false,"isRinOptimized":false},{"Mode":"voltage-clamp","Erev":-8.35,"Vm":-75.9,"Rin":100.0,"Rin_min":10.0,"Rin_max":400.0,"Cm":100.0,"Cm_min":10.0,"Cm_max":400.0,"g_syn":2.45,"g_syn_min":0.01,"g_syn_max":30.0,"tau_d":23.02,"tau_d_min":0.3,"tau_d_max":23.02,"tau_r":1.376,"tau_r_min":1.0,"tau_r_max":30000.0,"tau_f":8.003,"tau_f_min":1.0,"tau_f_max":30000.0,"U":0.332,"U_min":0.001,"U_max":0.999,"error":0.683,"isCmOptimized":false,"isRinOptimized":false},{"Mode":"voltage-clamp","Erev":-8.35,"Vm":-75.9,"Rin":100.0,"Rin_min":10.0,"Rin_max":400.0,"Cm":100.0,"Cm_min":10.0,"Cm_max":400.0,"g_syn":8.512,"g_syn_min":0.01,"g_syn_max":30.0,"tau_d":23.02,"tau_d_min":0.3,"tau_d_max":23.02,"tau_r":47.345,"tau_r_min":1.0,"tau_r_max":30000.0,"tau_f":6.484,"tau_f_min":1.0,"tau_f_max":30000.0,"U":0.099,"U_min":0.001,"U_max":0.999,"error":0.661,"isCmOptimized":false,"isRinOptimized":false},{"Mode":"voltage-clamp","Erev":-8.35,"Vm":-75.9,"Rin":100.0,"Rin_min":10.0,"Rin_max":400.0,"Cm":100.0,"Cm_min":10.0,"Cm_max":400.0,"g_syn":8.626,"g_syn_min":0.01,"g_syn_max":30.0,"tau_d":23.02,"tau_d_min":0.3,"tau_d_max":23.02,"tau_r":47.914,"tau_r_min":1.0,"tau_r_max":30000.0,"tau_f":6.36,"tau_f_min":1.0,"tau_f_max":30000.0,"U":0.097,"U_min":0.001,"U_max":0.999,"error":0.661,"isCmOptimized":false,"isRinOptimized":false},{"Mode":"voltage-clamp","Erev":-8.35,"Vm":-75.9,"Rin":100.0,"Rin_min":10.0,"Rin_max":400.0,"Cm":100.0,"Cm_min":10.0,"Cm_max":400.0,"g_syn":8.466,"g_syn_min":0.01,"g_syn_max":30.0,"tau_d":23.02,"tau_d_min":0.3,"tau_d_max":23.02,"tau_r":47.731,"tau_r_min":1.0,"tau_r_max":30000.0,"tau_f":6.59,"tau_f_min":1.0,"tau_f_max":30000.0,"U":0.099,"U_min":0.001,"U_max":0.999,"error":0.661,"isCmOptimized":false,"isRinOptimized":false},{"Mode":"voltage-clamp","Erev":-8.35,"Vm":-75.9,"Rin":100.0,"Rin_min":10.0,"Rin_max":400.0,"Cm":100.0,"Cm_min":10.0,"Cm_max":400.0,"g_syn":7.91,"g_syn_min":0.01,"g_syn_max":30.0,"tau_d":23.02,"tau_d_min":0.3,"tau_d_max":23.02,"tau_r":44.18,"tau_r_min":1.0,"tau_r_max":30000.0,"tau_f":6.784,"tau_f_min":1.0,"tau_f_max":30000.0,"U":0.106,"U_min":0.001,"U_max":0.999,"error":0.661,"isCmOptimized":false,"isRinOptimized":false},{"Mode":"voltage-clamp","Erev":-8.35,"Vm":-75.9,"Rin":100.0,"Rin_min":10.0,"Rin_max":400.0,"Cm":100.0,"Cm_min":10.0,"Cm_max":400.0,"g_syn":8.599,"g_syn_min":0.01,"g_syn_max":30.0,"tau_d":23.02,"tau_d_min":0.3,"tau_d_max":23.02,"tau_r":48.289,"tau_r_min":1.0,"tau_r_max":30000.0,"tau_f":6.516,"tau_f_min":1.0,"tau_f_max":30000.0,"U":0.098,"U_min":0.001,"U_max":0.999,"error":0.661,"isCmOptimized":false,"isRinOptimized":false},{"Mode":"voltage-clamp","Erev":-8.35,"Vm":-75.9,"Rin":100.0,"Rin_min":10.0,"Rin_max":400.0,"Cm":100.0,"Cm_min":10.0,"Cm_max":400.0,"g_syn":7.91,"g_syn_min":0.01,"g_syn_max":30.0,"tau_d":23.02,"tau_d_min":0.3,"tau_d_max":23.02,"tau_r":43.618,"tau_r_min":1.0,"tau_r_max":30000.0,"tau_f":6.648,"tau_f_min":1.0,"tau_f_max":30000.0,"U":0.106,"U_min":0.001,"U_max":0.999,"error":0.661,"isCmOptimized":false,"isRinOptimized":false},{"Mode":"voltage-clamp","Erev":-8.35,"Vm":-75.9,"Rin":100.0,"Rin_min":10.0,"Rin_max":400.0,"Cm":100.0,"Cm_min":10.0,"Cm_max":400.0,"g_syn":7.938,"g_syn_min":0.01,"g_syn_max":30.0,"tau_d":23.02,"tau_d_min":0.3,"tau_d_max":23.02,"tau_r":45.573,"tau_r_min":1.0,"tau_r_max":30000.0,"tau_f":6.956,"tau_f_min":1.0,"tau_f_max":30000.0,"U":0.106,"U_min":0.001,"U_max":0.999,"error":0.661,"isCmOptimized":false,"isRinOptimized":false},{"Mode":"voltage-clamp","Erev":-8.35,"Vm":-75.9,"Rin":100.0,"Rin_min":10.0,"Rin_max":400.0,"Cm":100.0,"Cm_min":10.0,"Cm_max":400.0,"g_syn":9.011,"g_syn_min":0.01,"g_syn_max":30.0,"tau_d":23.02,"tau_d_min":0.3,"tau_d_max":23.02,"tau_r":50.414,"tau_r_min":1.0,"tau_r_max":30000.0,"tau_f":6.274,"tau_f_min":1.0,"tau_f_max":30000.0,"U":0.093,"U_min":0.001,"U_max":0.999,"error":0.661,"isCmOptimized":false,"isRinOptimized":false},{"Mode":"voltage-clamp","Erev":-8.35,"Vm":-75.9,"Rin":100.0,"Rin_min":10.0,"Rin_max":400.0,"Cm":100.0,"Cm_min":10.0,"Cm_max":400.0,"g_syn":8.375,"g_syn_min":0.01,"g_syn_max":30.0,"tau_d":23.02,"tau_d_min":0.3,"tau_d_max":23.02,"tau_r":46.72,"tau_r_min":1.0,"tau_r_max":30000.0,"tau_f":6.531,"tau_f_min":1.0,"tau_f_max":30000.0,"U":0.1,"U_min":0.001,"U_max":0.999,"error":0.661,"isCmOptimized":false,"isRinOptimized":false},{"Mode":"voltage-clamp","Erev":-8.35,"Vm":-75.9,"Rin":100.0,"Rin_min":10.0,"Rin_max":400.0,"Cm":100.0,"Cm_min":10.0,"Cm_max":400.0,"g_syn":8.272,"g_syn_min":0.01,"g_syn_max":30.0,"tau_d":23.02,"tau_d_min":0.3,"tau_d_max":23.02,"tau_r":46.351,"tau_r_min":1.0,"tau_r_max":30000.0,"tau_f":6.634,"tau_f_min":1.0,"tau_f_max":30000.0,"U":0.102,"U_min":0.001,"U_max":0.999,"error":0.661,"isCmOptimized":false,"isRinOptimized":false},{"Mode":"voltage-clamp","Erev":-8.35,"Vm":-75.9,"Rin":100.0,"Rin_min":10.0,"Rin_max":400.0,"Cm":100.0,"Cm_min":10.0,"Cm_max":400.0,"g_syn":8.618,"g_syn_min":0.01,"g_syn_max":30.0,"tau_d":23.02,"tau_d_min":0.3,"tau_d_max":23.02,"tau_r":48.052,"tau_r_min":1.0,"tau_r_max":30000.0,"tau_f":6.349,"tau_f_min":1.0,"tau_f_max":30000.0,"U":0.098,"U_min":0.001,"U_max":0.999,"error":0.661,"isCmOptimized":false,"isRinOptimized":false},{"Mode":"voltage-clamp","Erev":-8.35,"Vm":-75.9,"Rin":100.0,"Rin_min":10.0,"Rin_max":400.0,"Cm":100.0,"Cm_min":10.0,"Cm_max":400.0,"g_syn":2.473,"g_syn_min":0.01,"g_syn_max":30.0,"tau_d":23.02,"tau_d_min":0.3,"tau_d_max":23.02,"tau_r":1.218,"tau_r_min":1.0,"tau_r_max":30000.0,"tau_f":7.706,"tau_f_min":1.0,"tau_f_max":30000.0,"U":0.329,"U_min":0.001,"U_max":0.999,"error":0.683,"isCmOptimized":false,"isRinOptimized":false},{"Mode":"voltage-clamp","Erev":-8.35,"Vm":-75.9,"Rin":100.0,"Rin_min":10.0,"Rin_max":400.0,"Cm":100.0,"Cm_min":10.0,"Cm_max":400.0,"g_syn":9.266,"g_syn_min":0.01,"g_syn_max":30.0,"tau_d":23.02,"tau_d_min":0.3,"tau_d_max":23.02,"tau_r":52.19,"tau_r_min":1.0,"tau_r_max":30000.0,"tau_f":6.193,"tau_f_min":1.0,"tau_f_max":30000.0,"U":0.091,"U_min":0.001,"U_max":0.999,"error":0.661,"isCmOptimized":false,"isRinOptimized":false},{"Mode":"voltage-clamp","Erev":-8.35,"Vm":-75.9,"Rin":100.0,"Rin_min":10.0,"Rin_max":400.0,"Cm":100.0,"Cm_min":10.0,"Cm_max":400.0,"g_syn":9.32,"g_syn_min":0.01,"g_syn_max":30.0,"tau_d":23.02,"tau_d_min":0.3,"tau_d_max":23.02,"tau_r":51.449,"tau_r_min":1.0,"tau_r_max":30000.0,"tau_f":6.054,"tau_f_min":1.0,"tau_f_max":30000.0,"U":0.09,"U_min":0.001,"U_max":0.999,"error":0.661,"isCmOptimized":false,"isRinOptimized":false},{"Mode":"voltage-clamp","Erev":-8.35,"Vm":-75.9,"Rin":100.0,"Rin_min":10.0,"Rin_max":400.0,"Cm":100.0,"Cm_min":10.0,"Cm_max":400.0,"g_syn":9.17,"g_syn_min":0.01,"g_syn_max":30.0,"tau_d":23.02,"tau_d_min":0.3,"tau_d_max":23.02,"tau_r":49.719,"tau_r_min":1.0,"tau_r_max":30000.0,"tau_f":5.969,"tau_f_min":1.0,"tau_f_max":30000.0,"U":0.092,"U_min":0.001,"U_max":0.999,"error":0.661,"isCmOptimized":false,"isRinOptimized":false},{"Mode":"voltage-clamp","Erev":-8.35,"Vm":-75.9,"Rin":100.0,"Rin_min":10.0,"Rin_max":400.0,"Cm":100.0,"Cm_min":10.0,"Cm_max":400.0,"g_syn":9.235,"g_syn_min":0.01,"g_syn_max":30.0,"tau_d":23.02,"tau_d_min":0.3,"tau_d_max":23.02,"tau_r":50.362,"tau_r_min":1.0,"tau_r_max":30000.0,"tau_f":5.921,"tau_f_min":1.0,"tau_f_max":30000.0,"U":0.091,"U_min":0.001,"U_max":0.999,"error":0.661,"isCmOptimized":false,"isRinOptimized":false},{"Mode":"voltage-clamp","Erev":-8.35,"Vm":-75.9,"Rin":100.0,"Rin_min":10.0,"Rin_max":400.0,"Cm":100.0,"Cm_min":10.0,"Cm_max":400.0,"g_syn":9.852,"g_syn_min":0.01,"g_syn_max":30.0,"tau_d":23.02,"tau_d_min":0.3,"tau_d_max":23.02,"tau_r":53.47,"tau_r_min":1.0,"tau_r_max":30000.0,"tau_f":5.684,"tau_f_min":1.0,"tau_f_max":30000.0,"U":0.085,"U_min":0.001,"U_max":0.999,"error":0.661,"isCmOptimized":false,"isRinOptimized":false},{"Mode":"voltage-clamp","Erev":-8.35,"Vm":-75.9,"Rin":100.0,"Rin_min":10.0,"Rin_max":400.0,"Cm":100.0,"Cm_min":10.0,"Cm_max":400.0,"g_syn":9.104,"g_syn_min":0.01,"g_syn_max":30.0,"tau_d":23.02,"tau_d_min":0.3,"tau_d_max":23.02,"tau_r":50.052,"tau_r_min":1.0,"tau_r_max":30000.0,"tau_f":5.917,"tau_f_min":1.0,"tau_f_max":30000.0,"U":0.093,"U_min":0.001,"U_max":0.999,"error":0.661,"isCmOptimized":false,"isRinOptimized":false},{"Mode":"voltage-clamp","Erev":-8.35,"Vm":-75.9,"Rin":100.0,"Rin_min":10.0,"Rin_max":400.0,"Cm":100.0,"Cm_min":10.0,"Cm_max":400.0,"g_syn":8.753,"g_syn_min":0.01,"g_syn_max":30.0,"tau_d":23.02,"tau_d_min":0.3,"tau_d_max":23.02,"tau_r":50.337,"tau_r_min":1.0,"tau_r_max":30000.0,"tau_f":6.576,"tau_f_min":1.0,"tau_f_max":30000.0,"U":0.096,"U_min":0.001,"U_max":0.999,"error":0.661,"isCmOptimized":false,"isRinOptimized":false},{"Mode":"voltage-clamp","Erev":-8.35,"Vm":-75.9,"Rin":100.0,"Rin_min":10.0,"Rin_max":400.0,"Cm":100.0,"Cm_min":10.0,"Cm_max":400.0,"g_syn":8.955,"g_syn_min":0.01,"g_syn_max":30.0,"tau_d":23.02,"tau_d_min":0.3,"tau_d_max":23.02,"tau_r":48.27,"tau_r_min":1.0,"tau_r_max":30000.0,"tau_f":5.972,"tau_f_min":1.0,"tau_f_max":30000.0,"U":0.094,"U_min":0.001,"U_max":0.999,"error":0.661,"isCmOptimized":false,"isRinOptimized":false},{"Mode":"voltage-clamp","Erev":-8.35,"Vm":-75.9,"Rin":100.0,"Rin_min":10.0,"Rin_max":400.0,"Cm":100.0,"Cm_min":10.0,"Cm_max":400.0,"g_syn":8.557,"g_syn_min":0.01,"g_syn_max":30.0,"tau_d":23.02,"tau_d_min":0.3,"tau_d_max":23.02,"tau_r":47.201,"tau_r_min":1.0,"tau_r_max":30000.0,"tau_f":6.334,"tau_f_min":1.0,"tau_f_max":30000.0,"U":0.098,"U_min":0.001,"U_max":0.999,"error":0.661,"isCmOptimized":false,"isRinOptimized":false},{"Mode":"voltage-clamp","Erev":-8.35,"Vm":-75.9,"Rin":100.0,"Rin_min":10.0,"Rin_max":400.0,"Cm":100.0,"Cm_min":10.0,"Cm_max":400.0,"g_syn":8.684,"g_syn_min":0.01,"g_syn_max":30.0,"tau_d":23.02,"tau_d_min":0.3,"tau_d_max":23.02,"tau_r":47.38,"tau_r_min":1.0,"tau_r_max":30000.0,"tau_f":6.179,"tau_f_min":1.0,"tau_f_max":30000.0,"U":0.097,"U_min":0.001,"U_max":0.999,"error":0.661,"isCmOptimized":false,"isRinOptimized":false},{"Mode":"voltage-clamp","Erev":-8.35,"Vm":-75.9,"Rin":100.0,"Rin_min":10.0,"Rin_max":400.0,"Cm":100.0,"Cm_min":10.0,"Cm_max":400.0,"g_syn":8.046,"g_syn_min":0.01,"g_syn_max":30.0,"tau_d":23.02,"tau_d_min":0.3,"tau_d_max":23.02,"tau_r":45.178,"tau_r_min":1.0,"tau_r_max":30000.0,"tau_f":6.772,"tau_f_min":1.0,"tau_f_max":30000.0,"U":0.104,"U_min":0.001,"U_max":0.999,"error":0.661,"isCmOptimized":false,"isRinOptimized":false},{"Mode":"voltage-clamp","Erev":-8.35,"Vm":-75.9,"Rin":100.0,"Rin_min":10.0,"Rin_max":400.0,"Cm":100.0,"Cm_min":10.0,"Cm_max":400.0,"g_syn":8.382,"g_syn_min":0.01,"g_syn_max":30.0,"tau_d":23.02,"tau_d_min":0.3,"tau_d_max":23.02,"tau_r":47.096,"tau_r_min":1.0,"tau_r_max":30000.0,"tau_f":6.608,"tau_f_min":1.0,"tau_f_max":30000.0,"U":0.1,"U_min":0.001,"U_max":0.999,"error":0.661,"isCmOptimized":false,"isRinOptimized":false},{"Mode":"voltage-clamp","Erev":-8.35,"Vm":-75.9,"Rin":100.0,"Rin_min":10.0,"Rin_max":400.0,"Cm":100.0,"Cm_min":10.0,"Cm_max":400.0,"g_syn":9.972,"g_syn_min":0.01,"g_syn_max":30.0,"tau_d":23.02,"tau_d_min":0.3,"tau_d_max":23.02,"tau_r":55.438,"tau_r_min":1.0,"tau_r_max":30000.0,"tau_f":5.826,"tau_f_min":1.0,"tau_f_max":30000.0,"U":0.084,"U_min":0.001,"U_max":0.999,"error":0.661,"isCmOptimized":false,"isRinOptimized":false},{"Mode":"voltage-clamp","Erev":-8.35,"Vm":-75.9,"Rin":100.0,"Rin_min":10.0,"Rin_max":400.0,"Cm":100.0,"Cm_min":10.0,"Cm_max":400.0,"g_syn":8.746,"g_syn_min":0.01,"g_syn_max":30.0,"tau_d":23.02,"tau_d_min":0.3,"tau_d_max":23.02,"tau_r":47.763,"tau_r_min":1.0,"tau_r_max":30000.0,"tau_f":6.161,"tau_f_min":1.0,"tau_f_max":30000.0,"U":0.096,"U_min":0.001,"U_max":0.999,"error":0.661,"isCmOptimized":false,"isRinOptimized":false},{"Mode":"voltage-clamp","Erev":-8.35,"Vm":-75.9,"Rin":100.0,"Rin_min":10.0,"Rin_max":400.0,"Cm":100.0,"Cm_min":10.0,"Cm_max":400.0,"g_syn":9.516,"g_syn_min":0.01,"g_syn_max":30.0,"tau_d":23.02,"tau_d_min":0.3,"tau_d_max":23.02,"tau_r":52.185,"tau_r_min":1.0,"tau_r_max":30000.0,"tau_f":5.878,"tau_f_min":1.0,"tau_f_max":30000.0,"U":0.088,"U_min":0.001,"U_max":0.999,"error":0.661,"isCmOptimized":false,"isRinOptimized":false},{"Mode":"voltage-clamp","Erev":-8.35,"Vm":-75.9,"Rin":100.0,"Rin_min":10.0,"Rin_max":400.0,"Cm":100.0,"Cm_min":10.0,"Cm_max":400.0,"g_syn":2.533,"g_syn_min":0.01,"g_syn_max":30.0,"tau_d":23.02,"tau_d_min":0.3,"tau_d_max":23.02,"tau_r":2.11,"tau_r_min":1.0,"tau_r_max":30000.0,"tau_f":7.979,"tau_f_min":1.0,"tau_f_max":30000.0,"U":0.321,"U_min":0.001,"U_max":0.999,"error":0.683,"isCmOptimized":false,"isRinOptimized":false},{"Mode":"voltage-clamp","Erev":-8.35,"Vm":-75.9,"Rin":100.0,"Rin_min":10.0,"Rin_max":400.0,"Cm":100.0,"Cm_min":10.0,"Cm_max":400.0,"g_syn":8.567,"g_syn_min":0.01,"g_syn_max":30.0,"tau_d":23.02,"tau_d_min":0.3,"tau_d_max":23.02,"tau_r":47.734,"tau_r_min":1.0,"tau_r_max":30000.0,"tau_f":6.417,"tau_f_min":1.0,"tau_f_max":30000.0,"U":0.098,"U_min":0.001,"U_max":0.999,"error":0.661,"isCmOptimized":false,"isRinOptimized":false},{"Mode":"voltage-clamp","Erev":-8.35,"Vm":-75.9,"Rin":100.0,"Rin_min":10.0,"Rin_max":400.0,"Cm":100.0,"Cm_min":10.0,"Cm_max":400.0,"g_syn":9.092,"g_syn_min":0.01,"g_syn_max":30.0,"tau_d":23.02,"tau_d_min":0.3,"tau_d_max":23.02,"tau_r":50.943,"tau_r_min":1.0,"tau_r_max":30000.0,"tau_f":5.92,"tau_f_min":1.0,"tau_f_max":30000.0,"U":0.093,"U_min":0.001,"U_max":0.999,"error":0.661,"isCmOptimized":false,"isRinOptimized":false},{"Mode":"voltage-clamp","Erev":-8.35,"Vm":-75.9,"Rin":100.0,"Rin_min":10.0,"Rin_max":400.0,"Cm":100.0,"Cm_min":10.0,"Cm_max":400.0,"g_syn":9.599,"g_syn_min":0.01,"g_syn_max":30.0,"tau_d":23.02,"tau_d_min":0.3,"tau_d_max":23.02,"tau_r":53.468,"tau_r_min":1.0,"tau_r_max":30000.0,"tau_f":6.014,"tau_f_min":1.0,"tau_f_max":30000.0,"U":0.087,"U_min":0.001,"U_max":0.999,"error":0.661,"isCmOptimized":false,"isRinOptimized":false},{"Mode":"voltage-clamp","Erev":-8.35,"Vm":-75.9,"Rin":100.0,"Rin_min":10.0,"Rin_max":400.0,"Cm":100.0,"Cm_min":10.0,"Cm_max":400.0,"g_syn":8.799,"g_syn_min":0.01,"g_syn_max":30.0,"tau_d":23.02,"tau_d_min":0.3,"tau_d_max":23.02,"tau_r":47.836,"tau_r_min":1.0,"tau_r_max":30000.0,"tau_f":6.197,"tau_f_min":1.0,"tau_f_max":30000.0,"U":0.095,"U_min":0.001,"U_max":0.999,"error":0.661,"isCmOptimized":false,"isRinOptimized":false},{"Mode":"voltage-clamp","Erev":-8.35,"Vm":-75.9,"Rin":100.0,"Rin_min":10.0,"Rin_max":400.0,"Cm":100.0,"Cm_min":10.0,"Cm_max":400.0,"g_syn":8.909,"g_syn_min":0.01,"g_syn_max":30.0,"tau_d":23.02,"tau_d_min":0.3,"tau_d_max":23.02,"tau_r":49.555,"tau_r_min":1.0,"tau_r_max":30000.0,"tau_f":6.017,"tau_f_min":1.0,"tau_f_max":30000.0,"U":0.095,"U_min":0.001,"U_max":0.999,"error":0.661,"isCmOptimized":false,"isRinOptimized":false},{"Mode":"voltage-clamp","Erev":-8.35,"Vm":-75.9,"Rin":100.0,"Rin_min":10.0,"Rin_max":400.0,"Cm":100.0,"Cm_min":10.0,"Cm_max":400.0,"g_syn":8.342,"g_syn_min":0.01,"g_syn_max":30.0,"tau_d":23.02,"tau_d_min":0.3,"tau_d_max":23.02,"tau_r":46.779,"tau_r_min":1.0,"tau_r_max":30000.0,"tau_f":6.605,"tau_f_min":1.0,"tau_f_max":30000.0,"U":0.101,"U_min":0.001,"U_max":0.999,"error":0.661,"isCmOptimized":false,"isRinOptimized":false},{"Mode":"voltage-clamp","Erev":-8.35,"Vm":-75.9,"Rin":100.0,"Rin_min":10.0,"Rin_max":400.0,"Cm":100.0,"Cm_min":10.0,"Cm_max":400.0,"g_syn":6.806,"g_syn_min":0.01,"g_syn_max":30.0,"tau_d":23.02,"tau_d_min":0.3,"tau_d_max":23.02,"tau_r":37.859,"tau_r_min":1.0,"tau_r_max":30000.0,"tau_f":7.315,"tau_f_min":1.0,"tau_f_max":30000.0,"U":0.124,"U_min":0.001,"U_max":0.999,"error":0.662,"isCmOptimized":false,"isRinOptimized":false},{"Mode":"voltage-clamp","Erev":-8.35,"Vm":-75.9,"Rin":100.0,"Rin_min":10.0,"Rin_max":400.0,"Cm":100.0,"Cm_min":10.0,"Cm_max":400.0,"g_syn":8.449,"g_syn_min":0.01,"g_syn_max":30.0,"tau_d":23.02,"tau_d_min":0.3,"tau_d_max":23.02,"tau_r":47.414,"tau_r_min":1.0,"tau_r_max":30000.0,"tau_f":6.426,"tau_f_min":1.0,"tau_f_max":30000.0,"U":0.1,"U_min":0.001,"U_max":0.999,"error":0.661,"isCmOptimized":false,"isRinOptimized":false},{"Mode":"voltage-clamp","Erev":-8.35,"Vm":-75.9,"Rin":100.0,"Rin_min":10.0,"Rin_max":400.0,"Cm":100.0,"Cm_min":10.0,"Cm_max":400.0,"g_syn":9.118,"g_syn_min":0.01,"g_syn_max":30.0,"tau_d":23.02,"tau_d_min":0.3,"tau_d_max":23.02,"tau_r":50.475,"tau_r_min":1.0,"tau_r_max":30000.0,"tau_f":5.986,"tau_f_min":1.0,"tau_f_max":30000.0,"U":0.092,"U_min":0.001,"U_max":0.999,"error":0.661,"isCmOptimized":false,"isRinOptimized":false},{"Mode":"voltage-clamp","Erev":-8.35,"Vm":-75.9,"Rin":100.0,"Rin_min":10.0,"Rin_max":400.0,"Cm":100.0,"Cm_min":10.0,"Cm_max":400.0,"g_syn":8.285,"g_syn_min":0.01,"g_syn_max":30.0,"tau_d":23.02,"tau_d_min":0.3,"tau_d_max":23.02,"tau_r":45.648,"tau_r_min":1.0,"tau_r_max":30000.0,"tau_f":6.456,"tau_f_min":1.0,"tau_f_max":30000.0,"U":0.101,"U_min":0.001,"U_max":0.999,"error":0.661,"isCmOptimized":false,"isRinOptimized":false},{"Mode":"voltage-clamp","Erev":-8.35,"Vm":-75.9,"Rin":100.0,"Rin_min":10.0,"Rin_max":400.0,"Cm":100.0,"Cm_min":10.0,"Cm_max":400.0,"g_syn":8.253,"g_syn_min":0.01,"g_syn_max":30.0,"tau_d":23.02,"tau_d_min":0.3,"tau_d_max":23.02,"tau_r":46.922,"tau_r_min":1.0,"tau_r_max":30000.0,"tau_f":6.741,"tau_f_min":1.0,"tau_f_max":30000.0,"U":0.102,"U_min":0.001,"U_max":0.999,"error":0.661,"isCmOptimized":false,"isRinOptimized":false},{"Mode":"voltage-clamp","Erev":-8.35,"Vm":-75.9,"Rin":100.0,"Rin_min":10.0,"Rin_max":400.0,"Cm":100.0,"Cm_min":10.0,"Cm_max":400.0,"g_syn":8.565,"g_syn_min":0.01,"g_syn_max":30.0,"tau_d":23.02,"tau_d_min":0.3,"tau_d_max":23.02,"tau_r":48.675,"tau_r_min":1.0,"tau_r_max":30000.0,"tau_f":6.534,"tau_f_min":1.0,"tau_f_max":30000.0,"U":0.098,"U_min":0.001,"U_max":0.999,"error":0.661,"isCmOptimized":false,"isRinOptimized":false}]