[{"Mode":"current-clamp","Erev":-8.14,"Vm":-65.0,"Rin":101.0,"Rin_min":10.0,"Rin_max":800.0,"Cm":163.37,"Cm_min":10.0,"Cm_max":1200.0,"g_syn":0.968,"g_syn_min":0.01,"g_syn_max":30.0,"tau_d":38.228,"tau_d_min":0.3,"tau_d_max":40.0,"tau_r":15221.591,"tau_r_min":1.0,"tau_r_max":30000.0,"tau_f":27147.608,"tau_f_min":1.0,"tau_f_max":30000.0,"U":0.999,"U_min":0.001,"U_max":0.999,"error":1.801,"isCmOptimized":false,"isRinOptimized":false},{"Mode":"current-clamp","Erev":-8.14,"Vm":-65.0,"Rin":101.0,"Rin_min":10.0,"Rin_max":800.0,"Cm":163.37,"Cm_min":10.0,"Cm_max":1200.0,"g_syn":0.971,"g_syn_min":0.01,"g_syn_max":30.0,"tau_d":37.9,"tau_d_min":0.3,"tau_d_max":40.0,"tau_r":18268.475,"tau_r_min":1.0,"tau_r_max":30000.0,"tau_f":23604.619,"tau_f_min":1.0,"tau_f_max":30000.0,"U":0.999,"U_min":0.001,"U_max":0.999,"error":1.801,"isCmOptimized":false,"isRinOptimized":false},{"Mode":"current-clamp","Erev":-8.14,"Vm":-65.0,"Rin":101.0,"Rin_min":10.0,"Rin_max":800.0,"Cm":163.37,"Cm_min":10.0,"Cm_max":1200.0,"g_syn":0.966,"g_syn_min":0.01,"g_syn_max":30.0,"tau_d":38.168,"tau_d_min":0.3,"tau_d_max":40.0,"tau_r":20724.846,"tau_r_min":1.0,"tau_r_max":30000.0,"tau_f":23721.478,"tau_f_min":1.0,"tau_f_max":30000.0,"U":0.999,"U_min":0.001,"U_max":0.999,"error":1.801,"isCmOptimized":false,"isRinOptimized":false},{"Mode":"current-clamp","Erev":-8.14,"Vm":-65.0,"Rin":101.0,"Rin_min":10.0,"Rin_max":800.0,"Cm":163.37,"Cm_min":10.0,"Cm_max":1200.0,"g_syn":0.968,"g_syn_min":0.01,"g_syn_max":30.0,"tau_d":38.166,"tau_d_min":0.3,"tau_d_max":40.0,"tau_r":14057.819,"tau_r_min":1.0,"tau_r_max":30000.0,"tau_f":5741.974,"tau_f_min":1.0,"tau_f_max":30000.0,"U":0.999,"U_min":0.001,"U_max":0.999,"error":1.801,"isCmOptimized":false,"isRinOptimized":false},{"Mode":"current-clamp","Erev":-8.14,"Vm":-65.0,"Rin":101.0,"Rin_min":10.0,"Rin_max":800.0,"Cm":163.37,"Cm_min":10.0,"Cm_max":1200.0,"g_syn":0.967,"g_syn_min":0.01,"g_syn_max":30.0,"tau_d":38.265,"tau_d_min":0.3,"tau_d_max":40.0,"tau_r":25115.408,"tau_r_min":1.0,"tau_r_max":30000.0,"tau_f":1155.012,"tau_f_min":1.0,"tau_f_max":30000.0,"U":0.999,"U_min":0.001,"U_max":0.999,"error":1.801,"isCmOptimized":false,"isRinOptimized":false},{"Mode":"current-clamp","Erev":-8.14,"Vm":-65.0,"Rin":101.0,"Rin_min":10.0,"Rin_max":800.0,"Cm":163.37,"Cm_min":10.0,"Cm_max":1200.0,"g_syn":0.969,"g_syn_min":0.01,"g_syn_max":30.0,"tau_d":38.126,"tau_d_min":0.3,"tau_d_max":40.0,"tau_r":18669.985,"tau_r_min":1.0,"tau_r_max":30000.0,"tau_f":18177.788,"tau_f_min":1.0,"tau_f_max":30000.0,"U":0.999,"U_min":0.001,"U_max":0.999,"error":1.801,"isCmOptimized":false,"isRinOptimized":false},{"Mode":"current-clamp","Erev":-8.14,"Vm":-65.0,"Rin":101.0,"Rin_min":10.0,"Rin_max":800.0,"Cm":163.37,"Cm_min":10.0,"Cm_max":1200.0,"g_syn":0.967,"g_syn_min":0.01,"g_syn_max":30.0,"tau_d":38.263,"tau_d_min":0.3,"tau_d_max":40.0,"tau_r":17646.187,"tau_r_min":1.0,"tau_r_max":30000.0,"tau_f":8648.327,"tau_f_min":1.0,"tau_f_max":30000.0,"U":0.999,"U_min":0.001,"U_max":0.999,"error":1.801,"isCmOptimized":false,"isRinOptimized":false},{"Mode":"current-clamp","Erev":-8.14,"Vm":-65.0,"Rin":101.0,"Rin_min":10.0,"Rin_max":800.0,"Cm":163.37,"Cm_min":10.0,"Cm_max":1200.0,"g_syn":0.968,"g_syn_min":0.01,"g_syn_max":30.0,"tau_d":38.165,"tau_d_min":0.3,"tau_d_max":40.0,"tau_r":6344.414,"tau_r_min":1.0,"tau_r_max":30000.0,"tau_f":17828.293,"tau_f_min":1.0,"tau_f_max":30000.0,"U":0.999,"U_min":0.001,"U_max":0.999,"error":1.801,"isCmOptimized":false,"isRinOptimized":false},{"Mode":"current-clamp","Erev":-8.14,"Vm":-65.0,"Rin":101.0,"Rin_min":10.0,"Rin_max":800.0,"Cm":163.37,"Cm_min":10.0,"Cm_max":1200.0,"g_syn":0.967,"g_syn_min":0.01,"g_syn_max":30.0,"tau_d":38.264,"tau_d_min":0.3,"tau_d_max":40.0,"tau_r":6061.364,"tau_r_min":1.0,"tau_r_max":30000.0,"tau_f":12533.701,"tau_f_min":1.0,"tau_f_max":30000.0,"U":0.999,"U_min":0.001,"U_max":0.999,"error":1.801,"isCmOptimized":false,"isRinOptimized":false},{"Mode":"current-clamp","Erev":-8.14,"Vm":-65.0,"Rin":101.0,"Rin_min":10.0,"Rin_max":800.0,"Cm":163.37,"Cm_min":10.0,"Cm_max":1200.0,"g_syn":0.967,"g_syn_min":0.01,"g_syn_max":30.0,"tau_d":38.265,"tau_d_min":0.3,"tau_d_max":40.0,"tau_r":26182.064,"tau_r_min":1.0,"tau_r_max":30000.0,"tau_f":28779.769,"tau_f_min":1.0,"tau_f_max":30000.0,"U":0.999,"U_min":0.001,"U_max":0.999,"error":1.801,"isCmOptimized":false,"isRinOptimized":false},{"Mode":"current-clamp","Erev":-8.14,"Vm":-65.0,"Rin":101.0,"Rin_min":10.0,"Rin_max":800.0,"Cm":163.37,"Cm_min":10.0,"Cm_max":1200.0,"g_syn":0.967,"g_syn_min":0.01,"g_syn_max":30.0,"tau_d":38.305,"tau_d_min":0.3,"tau_d_max":40.0,"tau_r":20594.842,"tau_r_min":1.0,"tau_r_max":30000.0,"tau_f":13765.033,"tau_f_min":1.0,"tau_f_max":30000.0,"U":0.999,"U_min":0.001,"U_max":0.999,"error":1.801,"isCmOptimized":false,"isRinOptimized":false},{"Mode":"current-clamp","Erev":-8.14,"Vm":-65.0,"Rin":101.0,"Rin_min":10.0,"Rin_max":800.0,"Cm":163.37,"Cm_min":10.0,"Cm_max":1200.0,"g_syn":0.967,"g_syn_min":0.01,"g_syn_max":30.0,"tau_d":38.265,"tau_d_min":0.3,"tau_d_max":40.0,"tau_r":21132.79,"tau_r_min":1.0,"tau_r_max":30000.0,"tau_f":10554.034,"tau_f_min":1.0,"tau_f_max":30000.0,"U":0.999,"U_min":0.001,"U_max":0.999,"error":1.801,"isCmOptimized":false,"isRinOptimized":false},{"Mode":"current-clamp","Erev":-8.14,"Vm":-65.0,"Rin":101.0,"Rin_min":10.0,"Rin_max":800.0,"Cm":163.37,"Cm_min":10.0,"Cm_max":1200.0,"g_syn":0.964,"g_syn_min":0.01,"g_syn_max":30.0,"tau_d":38.5,"tau_d_min":0.3,"tau_d_max":40.0,"tau_r":19745.886,"tau_r_min":1.0,"tau_r_max":30000.0,"tau_f":7249.499,"tau_f_min":1.0,"tau_f_max":30000.0,"U":0.999,"U_min":0.001,"U_max":0.999,"error":1.801,"isCmOptimized":false,"isRinOptimized":false},{"Mode":"current-clamp","Erev":-8.14,"Vm":-65.0,"Rin":101.0,"Rin_min":10.0,"Rin_max":800.0,"Cm":163.37,"Cm_min":10.0,"Cm_max":1200.0,"g_syn":0.966,"g_syn_min":0.01,"g_syn_max":30.0,"tau_d":38.309,"tau_d_min":0.3,"tau_d_max":40.0,"tau_r":26471.88,"tau_r_min":1.0,"tau_r_max":30000.0,"tau_f":14483.649,"tau_f_min":1.0,"tau_f_max":30000.0,"U":0.999,"U_min":0.001,"U_max":0.999,"error":1.801,"isCmOptimized":false,"isRinOptimized":false},{"Mode":"current-clamp","Erev":-8.14,"Vm":-65.0,"Rin":101.0,"Rin_min":10.0,"Rin_max":800.0,"Cm":163.37,"Cm_min":10.0,"Cm_max":1200.0,"g_syn":0.967,"g_syn_min":0.01,"g_syn_max":30.0,"tau_d":38.263,"tau_d_min":0.3,"tau_d_max":40.0,"tau_r":10264.849,"tau_r_min":1.0,"tau_r_max":30000.0,"tau_f":2850.759,"tau_f_min":1.0,"tau_f_max":30000.0,"U":0.999,"U_min":0.001,"U_max":0.999,"error":1.801,"isCmOptimized":false,"isRinOptimized":false},{"Mode":"current-clamp","Erev":-8.14,"Vm":-65.0,"Rin":101.0,"Rin_min":10.0,"Rin_max":800.0,"Cm":163.37,"Cm_min":10.0,"Cm_max":1200.0,"g_syn":0.964,"g_syn_min":0.01,"g_syn_max":30.0,"tau_d":38.483,"tau_d_min":0.3,"tau_d_max":40.0,"tau_r":10813.735,"tau_r_min":1.0,"tau_r_max":30000.0,"tau_f":8572.287,"tau_f_min":1.0,"tau_f_max":30000.0,"U":0.999,"U_min":0.001,"U_max":0.999,"error":1.801,"isCmOptimized":false,"isRinOptimized":false},{"Mode":"current-clamp","Erev":-8.14,"Vm":-65.0,"Rin":101.0,"Rin_min":10.0,"Rin_max":800.0,"Cm":163.37,"Cm_min":10.0,"Cm_max":1200.0,"g_syn":0.968,"g_syn_min":0.01,"g_syn_max":30.0,"tau_d":38.169,"tau_d_min":0.3,"tau_d_max":40.0,"tau_r":13036.082,"tau_r_min":1.0,"tau_r_max":30000.0,"tau_f":23026.656,"tau_f_min":1.0,"tau_f_max":30000.0,"U":0.999,"U_min":0.001,"U_max":0.999,"error":1.801,"isCmOptimized":false,"isRinOptimized":false},{"Mode":"current-clamp","Erev":-8.14,"Vm":-65.0,"Rin":101.0,"Rin_min":10.0,"Rin_max":800.0,"Cm":163.37,"Cm_min":10.0,"Cm_max":1200.0,"g_syn":0.967,"g_syn_min":0.01,"g_syn_max":30.0,"tau_d":38.263,"tau_d_min":0.3,"tau_d_max":40.0,"tau_r":26199.24,"tau_r_min":1.0,"tau_r_max":30000.0,"tau_f":6384.183,"tau_f_min":1.0,"tau_f_max":30000.0,"U":0.999,"U_min":0.001,"U_max":0.999,"error":1.801,"isCmOptimized":false,"isRinOptimized":false},{"Mode":"current-clamp","Erev":-8.14,"Vm":-65.0,"Rin":101.0,"Rin_min":10.0,"Rin_max":800.0,"Cm":163.37,"Cm_min":10.0,"Cm_max":1200.0,"g_syn":0.966,"g_syn_min":0.01,"g_syn_max":30.0,"tau_d":38.339,"tau_d_min":0.3,"tau_d_max":40.0,"tau_r":6796.989,"tau_r_min":1.0,"tau_r_max":30000.0,"tau_f":19224.806,"tau_f_min":1.0,"tau_f_max":30000.0,"U":0.999,"U_min":0.001,"U_max":0.999,"error":1.801,"isCmOptimized":false,"isRinOptimized":false},{"Mode":"current-clamp","Erev":-8.14,"Vm":-65.0,"Rin":101.0,"Rin_min":10.0,"Rin_max":800.0,"Cm":163.37,"Cm_min":10.0,"Cm_max":1200.0,"g_syn":0.967,"g_syn_min":0.01,"g_syn_max":30.0,"tau_d":38.265,"tau_d_min":0.3,"tau_d_max":40.0,"tau_r":19831.659,"tau_r_min":1.0,"tau_r_max":30000.0,"tau_f":22710.301,"tau_f_min":1.0,"tau_f_max":30000.0,"U":0.999,"U_min":0.001,"U_max":0.999,"error":1.801,"isCmOptimized":false,"isRinOptimized":false},{"Mode":"current-clamp","Erev":-8.14,"Vm":-65.0,"Rin":101.0,"Rin_min":10.0,"Rin_max":800.0,"Cm":163.37,"Cm_min":10.0,"Cm_max":1200.0,"g_syn":0.967,"g_syn_min":0.01,"g_syn_max":30.0,"tau_d":38.265,"tau_d_min":0.3,"tau_d_max":40.0,"tau_r":8046.331,"tau_r_min":1.0,"tau_r_max":30000.0,"tau_f":3854.11,"tau_f_min":1.0,"tau_f_max":30000.0,"U":0.999,"U_min":0.001,"U_max":0.999,"error":1.801,"isCmOptimized":false,"isRinOptimized":false},{"Mode":"current-clamp","Erev":-8.14,"Vm":-65.0,"Rin":101.0,"Rin_min":10.0,"Rin_max":800.0,"Cm":163.37,"Cm_min":10.0,"Cm_max":1200.0,"g_syn":0.968,"g_syn_min":0.01,"g_syn_max":30.0,"tau_d":38.212,"tau_d_min":0.3,"tau_d_max":40.0,"tau_r":4946.94,"tau_r_min":1.0,"tau_r_max":30000.0,"tau_f":25888.866,"tau_f_min":1.0,"tau_f_max":30000.0,"U":0.999,"U_min":0.001,"U_max":0.999,"error":1.801,"isCmOptimized":false,"isRinOptimized":false},{"Mode":"current-clamp","Erev":-8.14,"Vm":-65.0,"Rin":101.0,"Rin_min":10.0,"Rin_max":800.0,"Cm":163.37,"Cm_min":10.0,"Cm_max":1200.0,"g_syn":0.967,"g_syn_min":0.01,"g_syn_max":30.0,"tau_d":38.265,"tau_d_min":0.3,"tau_d_max":40.0,"tau_r":23577.689,"tau_r_min":1.0,"tau_r_max":30000.0,"tau_f":20518.668,"tau_f_min":1.0,"tau_f_max":30000.0,"U":0.999,"U_min":0.001,"U_max":0.999,"error":1.801,"isCmOptimized":false,"isRinOptimized":false},{"Mode":"current-clamp","Erev":-8.14,"Vm":-65.0,"Rin":101.0,"Rin_min":10.0,"Rin_max":800.0,"Cm":163.37,"Cm_min":10.0,"Cm_max":1200.0,"g_syn":0.969,"g_syn_min":0.01,"g_syn_max":30.0,"tau_d":38.134,"tau_d_min":0.3,"tau_d_max":40.0,"tau_r":18317.11,"tau_r_min":1.0,"tau_r_max":30000.0,"tau_f":27154.055,"tau_f_min":1.0,"tau_f_max":30000.0,"U":0.999,"U_min":0.001,"U_max":0.999,"error":1.801,"isCmOptimized":false,"isRinOptimized":false},{"Mode":"current-clamp","Erev":-8.14,"Vm":-65.0,"Rin":101.0,"Rin_min":10.0,"Rin_max":800.0,"Cm":163.37,"Cm_min":10.0,"Cm_max":1200.0,"g_syn":0.964,"g_syn_min":0.01,"g_syn_max":30.0,"tau_d":38.531,"tau_d_min":0.3,"tau_d_max":40.0,"tau_r":21724.321,"tau_r_min":1.0,"tau_r_max":30000.0,"tau_f":2653.856,"tau_f_min":1.0,"tau_f_max":30000.0,"U":0.999,"U_min":0.001,"U_max":0.999,"error":1.801,"isCmOptimized":false,"isRinOptimized":false},{"Mode":"current-clamp","Erev":-8.14,"Vm":-65.0,"Rin":101.0,"Rin_min":10.0,"Rin_max":800.0,"Cm":163.37,"Cm_min":10.0,"Cm_max":1200.0,"g_syn":0.967,"g_syn_min":0.01,"g_syn_max":30.0,"tau_d":38.264,"tau_d_min":0.3,"tau_d_max":40.0,"tau_r":16828.056,"tau_r_min":1.0,"tau_r_max":30000.0,"tau_f":6269.019,"tau_f_min":1.0,"tau_f_max":30000.0,"U":0.999,"U_min":0.001,"U_max":0.999,"error":1.801,"isCmOptimized":false,"isRinOptimized":false},{"Mode":"current-clamp","Erev":-8.14,"Vm":-65.0,"Rin":101.0,"Rin_min":10.0,"Rin_max":800.0,"Cm":163.37,"Cm_min":10.0,"Cm_max":1200.0,"g_syn":0.964,"g_syn_min":0.01,"g_syn_max":30.0,"tau_d":38.487,"tau_d_min":0.3,"tau_d_max":40.0,"tau_r":17369.369,"tau_r_min":1.0,"tau_r_max":30000.0,"tau_f":18875.518,"tau_f_min":1.0,"tau_f_max":30000.0,"U":0.999,"U_min":0.001,"U_max":0.999,"error":1.801,"isCmOptimized":false,"isRinOptimized":false},{"Mode":"current-clamp","Erev":-8.14,"Vm":-65.0,"Rin":101.0,"Rin_min":10.0,"Rin_max":800.0,"Cm":163.37,"Cm_min":10.0,"Cm_max":1200.0,"g_syn":0.967,"g_syn_min":0.01,"g_syn_max":30.0,"tau_d":38.262,"tau_d_min":0.3,"tau_d_max":40.0,"tau_r":11630.512,"tau_r_min":1.0,"tau_r_max":30000.0,"tau_f":11332.492,"tau_f_min":1.0,"tau_f_max":30000.0,"U":0.999,"U_min":0.001,"U_max":0.999,"error":1.801,"isCmOptimized":false,"isRinOptimized":false},{"Mode":"current-clamp","Erev":-8.14,"Vm":-65.0,"Rin":101.0,"Rin_min":10.0,"Rin_max":800.0,"Cm":163.37,"Cm_min":10.0,"Cm_max":1200.0,"g_syn":0.964,"g_syn_min":0.01,"g_syn_max":30.0,"tau_d":38.481,"tau_d_min":0.3,"tau_d_max":40.0,"tau_r":1312.64,"tau_r_min":1.0,"tau_r_max":30000.0,"tau_f":901.533,"tau_f_min":1.0,"tau_f_max":30000.0,"U":0.999,"U_min":0.001,"U_max":0.999,"error":1.801,"isCmOptimized":false,"isRinOptimized":false},{"Mode":"current-clamp","Erev":-8.14,"Vm":-65.0,"Rin":101.0,"Rin_min":10.0,"Rin_max":800.0,"Cm":163.37,"Cm_min":10.0,"Cm_max":1200.0,"g_syn":0.967,"g_syn_min":0.01,"g_syn_max":30.0,"tau_d":38.262,"tau_d_min":0.3,"tau_d_max":40.0,"tau_r":15448.43,"tau_r_min":1.0,"tau_r_max":30000.0,"tau_f":26427.266,"tau_f_min":1.0,"tau_f_max":30000.0,"U":0.999,"U_min":0.001,"U_max":0.999,"error":1.801,"isCmOptimized":false,"isRinOptimized":false},{"Mode":"current-clamp","Erev":-8.14,"Vm":-65.0,"Rin":101.0,"Rin_min":10.0,"Rin_max":800.0,"Cm":163.37,"Cm_min":10.0,"Cm_max":1200.0,"g_syn":0.967,"g_syn_min":0.01,"g_syn_max":30.0,"tau_d":38.264,"tau_d_min":0.3,"tau_d_max":40.0,"tau_r":10138.582,"tau_r_min":1.0,"tau_r_max":30000.0,"tau_f":29869.141,"tau_f_min":1.0,"tau_f_max":30000.0,"U":0.999,"U_min":0.001,"U_max":0.999,"error":1.801,"isCmOptimized":false,"isRinOptimized":false}]