[{"Mode":"voltage-clamp","Erev":-6.62,"Vm":-85.18,"Rin":100.0,"Rin_min":10.0,"Rin_max":400.0,"Cm":100.0,"Cm_min":10.0,"Cm_max":400.0,"g_syn":33.737,"g_syn_min":0.01,"g_syn_max":3000.0,"tau_d":8.008,"tau_d_min":0.3,"tau_d_max":10.0,"tau_r":50.0,"tau_r_min":50.0,"tau_r_max":30000.0,"tau_f":300.0,"tau_f_min":1.0,"tau_f_max":300.0,"U":0.001,"U_min":0.001,"U_max":0.001,"error":25.638,"isCmOptimized":false,"isRinOptimized":false},{"Mode":"voltage-clamp","Erev":-6.62,"Vm":-85.18,"Rin":100.0,"Rin_min":10.0,"Rin_max":400.0,"Cm":100.0,"Cm_min":10.0,"Cm_max":400.0,"g_syn":33.604,"g_syn_min":0.01,"g_syn_max":3000.0,"tau_d":8.063,"tau_d_min":0.3,"tau_d_max":10.0,"tau_r":50.292,"tau_r_min":50.0,"tau_r_max":30000.0,"tau_f":300.0,"tau_f_min":1.0,"tau_f_max":300.0,"U":0.001,"U_min":0.001,"U_max":0.001,"error":25.639,"isCmOptimized":false,"isRinOptimized":false},{"Mode":"voltage-clamp","Erev":-6.62,"Vm":-85.18,"Rin":100.0,"Rin_min":10.0,"Rin_max":400.0,"Cm":100.0,"Cm_min":10.0,"Cm_max":400.0,"g_syn":33.49,"g_syn_min":0.01,"g_syn_max":3000.0,"tau_d":8.076,"tau_d_min":0.3,"tau_d_max":10.0,"tau_r":50.169,"tau_r_min":50.0,"tau_r_max":30000.0,"tau_f":299.997,"tau_f_min":1.0,"tau_f_max":300.0,"U":0.001,"U_min":0.001,"U_max":0.001,"error":25.638,"isCmOptimized":false,"isRinOptimized":false},{"Mode":"voltage-clamp","Erev":-6.62,"Vm":-85.18,"Rin":100.0,"Rin_min":10.0,"Rin_max":400.0,"Cm":100.0,"Cm_min":10.0,"Cm_max":400.0,"g_syn":33.656,"g_syn_min":0.01,"g_syn_max":3000.0,"tau_d":8.037,"tau_d_min":0.3,"tau_d_max":10.0,"tau_r":50.03,"tau_r_min":50.0,"tau_r_max":30000.0,"tau_f":300.0,"tau_f_min":1.0,"tau_f_max":300.0,"U":0.001,"U_min":0.001,"U_max":0.001,"error":25.638,"isCmOptimized":false,"isRinOptimized":false},{"Mode":"voltage-clamp","Erev":-6.62,"Vm":-85.18,"Rin":100.0,"Rin_min":10.0,"Rin_max":400.0,"Cm":100.0,"Cm_min":10.0,"Cm_max":400.0,"g_syn":33.566,"g_syn_min":0.01,"g_syn_max":3000.0,"tau_d":8.069,"tau_d_min":0.3,"tau_d_max":10.0,"tau_r":50.0,"tau_r_min":50.0,"tau_r_max":30000.0,"tau_f":300.0,"tau_f_min":1.0,"tau_f_max":300.0,"U":0.001,"U_min":0.001,"U_max":0.001,"error":25.638,"isCmOptimized":false,"isRinOptimized":false},{"Mode":"voltage-clamp","Erev":-6.62,"Vm":-85.18,"Rin":100.0,"Rin_min":10.0,"Rin_max":400.0,"Cm":100.0,"Cm_min":10.0,"Cm_max":400.0,"g_syn":33.591,"g_syn_min":0.01,"g_syn_max":3000.0,"tau_d":8.073,"tau_d_min":0.3,"tau_d_max":10.0,"tau_r":50.065,"tau_r_min":50.0,"tau_r_max":30000.0,"tau_f":299.991,"tau_f_min":1.0,"tau_f_max":300.0,"U":0.001,"U_min":0.001,"U_max":0.001,"error":25.638,"isCmOptimized":false,"isRinOptimized":false},{"Mode":"voltage-clamp","Erev":-6.62,"Vm":-85.18,"Rin":100.0,"Rin_min":10.0,"Rin_max":400.0,"Cm":100.0,"Cm_min":10.0,"Cm_max":400.0,"g_syn":33.598,"g_syn_min":0.01,"g_syn_max":3000.0,"tau_d":8.087,"tau_d_min":0.3,"tau_d_max":10.0,"tau_r":50.211,"tau_r_min":50.0,"tau_r_max":30000.0,"tau_f":299.991,"tau_f_min":1.0,"tau_f_max":300.0,"U":0.001,"U_min":0.001,"U_max":0.001,"error":25.638,"isCmOptimized":false,"isRinOptimized":false},{"Mode":"voltage-clamp","Erev":-6.62,"Vm":-85.18,"Rin":100.0,"Rin_min":10.0,"Rin_max":400.0,"Cm":100.0,"Cm_min":10.0,"Cm_max":400.0,"g_syn":33.422,"g_syn_min":0.01,"g_syn_max":3000.0,"tau_d":8.114,"tau_d_min":0.3,"tau_d_max":10.0,"tau_r":50.0,"tau_r_min":50.0,"tau_r_max":30000.0,"tau_f":300.0,"tau_f_min":1.0,"tau_f_max":300.0,"U":0.001,"U_min":0.001,"U_max":0.001,"error":25.638,"isCmOptimized":false,"isRinOptimized":false},{"Mode":"voltage-clamp","Erev":-6.62,"Vm":-85.18,"Rin":100.0,"Rin_min":10.0,"Rin_max":400.0,"Cm":100.0,"Cm_min":10.0,"Cm_max":400.0,"g_syn":33.509,"g_syn_min":0.01,"g_syn_max":3000.0,"tau_d":8.081,"tau_d_min":0.3,"tau_d_max":10.0,"tau_r":50.063,"tau_r_min":50.0,"tau_r_max":30000.0,"tau_f":300.0,"tau_f_min":1.0,"tau_f_max":300.0,"U":0.001,"U_min":0.001,"U_max":0.001,"error":25.638,"isCmOptimized":false,"isRinOptimized":false},{"Mode":"voltage-clamp","Erev":-6.62,"Vm":-85.18,"Rin":100.0,"Rin_min":10.0,"Rin_max":400.0,"Cm":100.0,"Cm_min":10.0,"Cm_max":400.0,"g_syn":33.502,"g_syn_min":0.01,"g_syn_max":3000.0,"tau_d":8.095,"tau_d_min":0.3,"tau_d_max":10.0,"tau_r":50.0,"tau_r_min":50.0,"tau_r_max":30000.0,"tau_f":300.0,"tau_f_min":1.0,"tau_f_max":300.0,"U":0.001,"U_min":0.001,"U_max":0.001,"error":25.638,"isCmOptimized":false,"isRinOptimized":false},{"Mode":"voltage-clamp","Erev":-6.62,"Vm":-85.18,"Rin":100.0,"Rin_min":10.0,"Rin_max":400.0,"Cm":100.0,"Cm_min":10.0,"Cm_max":400.0,"g_syn":33.398,"g_syn_min":0.01,"g_syn_max":3000.0,"tau_d":8.095,"tau_d_min":0.3,"tau_d_max":10.0,"tau_r":50.111,"tau_r_min":50.0,"tau_r_max":30000.0,"tau_f":299.969,"tau_f_min":1.0,"tau_f_max":300.0,"U":0.001,"U_min":0.001,"U_max":0.001,"error":25.638,"isCmOptimized":false,"isRinOptimized":false},{"Mode":"voltage-clamp","Erev":-6.62,"Vm":-85.18,"Rin":100.0,"Rin_min":10.0,"Rin_max":400.0,"Cm":100.0,"Cm_min":10.0,"Cm_max":400.0,"g_syn":33.621,"g_syn_min":0.01,"g_syn_max":3000.0,"tau_d":8.079,"tau_d_min":0.3,"tau_d_max":10.0,"tau_r":50.046,"tau_r_min":50.0,"tau_r_max":30000.0,"tau_f":299.993,"tau_f_min":1.0,"tau_f_max":300.0,"U":0.001,"U_min":0.001,"U_max":0.001,"error":25.638,"isCmOptimized":false,"isRinOptimized":false},{"Mode":"voltage-clamp","Erev":-6.62,"Vm":-85.18,"Rin":100.0,"Rin_min":10.0,"Rin_max":400.0,"Cm":100.0,"Cm_min":10.0,"Cm_max":400.0,"g_syn":33.466,"g_syn_min":0.01,"g_syn_max":3000.0,"tau_d":8.095,"tau_d_min":0.3,"tau_d_max":10.0,"tau_r":50.572,"tau_r_min":50.0,"tau_r_max":30000.0,"tau_f":300.0,"tau_f_min":1.0,"tau_f_max":300.0,"U":0.001,"U_min":0.001,"U_max":0.001,"error":25.639,"isCmOptimized":false,"isRinOptimized":false},{"Mode":"voltage-clamp","Erev":-6.62,"Vm":-85.18,"Rin":100.0,"Rin_min":10.0,"Rin_max":400.0,"Cm":100.0,"Cm_min":10.0,"Cm_max":400.0,"g_syn":33.395,"g_syn_min":0.01,"g_syn_max":3000.0,"tau_d":8.132,"tau_d_min":0.3,"tau_d_max":10.0,"tau_r":50.0,"tau_r_min":50.0,"tau_r_max":30000.0,"tau_f":300.0,"tau_f_min":1.0,"tau_f_max":300.0,"U":0.001,"U_min":0.001,"U_max":0.001,"error":25.638,"isCmOptimized":false,"isRinOptimized":false},{"Mode":"voltage-clamp","Erev":-6.62,"Vm":-85.18,"Rin":100.0,"Rin_min":10.0,"Rin_max":400.0,"Cm":100.0,"Cm_min":10.0,"Cm_max":400.0,"g_syn":33.78,"g_syn_min":0.01,"g_syn_max":3000.0,"tau_d":8.021,"tau_d_min":0.3,"tau_d_max":10.0,"tau_r":50.1,"tau_r_min":50.0,"tau_r_max":30000.0,"tau_f":299.885,"tau_f_min":1.0,"tau_f_max":300.0,"U":0.001,"U_min":0.001,"U_max":0.001,"error":25.639,"isCmOptimized":false,"isRinOptimized":false}]