[{"Mode":"voltage-clamp","Erev":-83.24,"Vm":-11.34,"Rin":100.0,"Rin_min":10.0,"Rin_max":800.0,"Cm":100.0,"Cm_min":10.0,"Cm_max":1200.0,"g_syn":1.457,"g_syn_min":1.0,"g_syn_max":10.0,"tau_d":10.266,"tau_d_min":0.3,"tau_d_max":40.0,"tau_r":63.017,"tau_r_min":1.0,"tau_r_max":3000.0,"tau_f":40.837,"tau_f_min":1.0,"tau_f_max":3000.0,"U":0.104,"U_min":0.001,"U_max":0.999,"error":0.221,"isCmOptimized":false,"isRinOptimized":false},{"Mode":"voltage-clamp","Erev":-83.24,"Vm":-11.34,"Rin":100.0,"Rin_min":10.0,"Rin_max":800.0,"Cm":100.0,"Cm_min":10.0,"Cm_max":1200.0,"g_syn":2.17,"g_syn_min":1.0,"g_syn_max":10.0,"tau_d":10.277,"tau_d_min":0.3,"tau_d_max":40.0,"tau_r":69.852,"tau_r_min":1.0,"tau_r_max":3000.0,"tau_f":36.487,"tau_f_min":1.0,"tau_f_max":3000.0,"U":0.07,"U_min":0.001,"U_max":0.999,"error":0.221,"isCmOptimized":false,"isRinOptimized":false},{"Mode":"voltage-clamp","Erev":-83.24,"Vm":-11.34,"Rin":100.0,"Rin_min":10.0,"Rin_max":800.0,"Cm":100.0,"Cm_min":10.0,"Cm_max":1200.0,"g_syn":5.141,"g_syn_min":1.0,"g_syn_max":10.0,"tau_d":10.262,"tau_d_min":0.3,"tau_d_max":40.0,"tau_r":105.028,"tau_r_min":1.0,"tau_r_max":3000.0,"tau_f":32.87,"tau_f_min":1.0,"tau_f_max":3000.0,"U":0.03,"U_min":0.001,"U_max":0.999,"error":0.221,"isCmOptimized":false,"isRinOptimized":false},{"Mode":"voltage-clamp","Erev":-83.24,"Vm":-11.34,"Rin":100.0,"Rin_min":10.0,"Rin_max":800.0,"Cm":100.0,"Cm_min":10.0,"Cm_max":1200.0,"g_syn":3.519,"g_syn_min":1.0,"g_syn_max":10.0,"tau_d":10.27,"tau_d_min":0.3,"tau_d_max":40.0,"tau_r":83.12,"tau_r_min":1.0,"tau_r_max":3000.0,"tau_f":33.58,"tau_f_min":1.0,"tau_f_max":3000.0,"U":0.043,"U_min":0.001,"U_max":0.999,"error":0.221,"isCmOptimized":false,"isRinOptimized":false},{"Mode":"voltage-clamp","Erev":-83.24,"Vm":-11.34,"Rin":100.0,"Rin_min":10.0,"Rin_max":800.0,"Cm":100.0,"Cm_min":10.0,"Cm_max":1200.0,"g_syn":4.283,"g_syn_min":1.0,"g_syn_max":10.0,"tau_d":10.285,"tau_d_min":0.3,"tau_d_max":40.0,"tau_r":99.739,"tau_r_min":1.0,"tau_r_max":3000.0,"tau_f":33.824,"tau_f_min":1.0,"tau_f_max":3000.0,"U":0.035,"U_min":0.001,"U_max":0.999,"error":0.221,"isCmOptimized":false,"isRinOptimized":false},{"Mode":"voltage-clamp","Erev":-83.24,"Vm":-11.34,"Rin":100.0,"Rin_min":10.0,"Rin_max":800.0,"Cm":100.0,"Cm_min":10.0,"Cm_max":1200.0,"g_syn":7.942,"g_syn_min":1.0,"g_syn_max":10.0,"tau_d":10.257,"tau_d_min":0.3,"tau_d_max":40.0,"tau_r":112.798,"tau_r_min":1.0,"tau_r_max":3000.0,"tau_f":30.888,"tau_f_min":1.0,"tau_f_max":3000.0,"U":0.019,"U_min":0.001,"U_max":0.999,"error":0.222,"isCmOptimized":false,"isRinOptimized":false},{"Mode":"voltage-clamp","Erev":-83.24,"Vm":-11.34,"Rin":100.0,"Rin_min":10.0,"Rin_max":800.0,"Cm":100.0,"Cm_min":10.0,"Cm_max":1200.0,"g_syn":6.977,"g_syn_min":1.0,"g_syn_max":10.0,"tau_d":10.278,"tau_d_min":0.3,"tau_d_max":40.0,"tau_r":120.744,"tau_r_min":1.0,"tau_r_max":3000.0,"tau_f":31.957,"tau_f_min":1.0,"tau_f_max":3000.0,"U":0.022,"U_min":0.001,"U_max":0.999,"error":0.221,"isCmOptimized":false,"isRinOptimized":false},{"Mode":"voltage-clamp","Erev":-83.24,"Vm":-11.34,"Rin":100.0,"Rin_min":10.0,"Rin_max":800.0,"Cm":100.0,"Cm_min":10.0,"Cm_max":1200.0,"g_syn":7.337,"g_syn_min":1.0,"g_syn_max":10.0,"tau_d":10.266,"tau_d_min":0.3,"tau_d_max":40.0,"tau_r":123.679,"tau_r_min":1.0,"tau_r_max":3000.0,"tau_f":31.685,"tau_f_min":1.0,"tau_f_max":3000.0,"U":0.021,"U_min":0.001,"U_max":0.999,"error":0.221,"isCmOptimized":false,"isRinOptimized":false},{"Mode":"voltage-clamp","Erev":-83.24,"Vm":-11.34,"Rin":100.0,"Rin_min":10.0,"Rin_max":800.0,"Cm":100.0,"Cm_min":10.0,"Cm_max":1200.0,"g_syn":1.959,"g_syn_min":1.0,"g_syn_max":10.0,"tau_d":10.233,"tau_d_min":0.3,"tau_d_max":40.0,"tau_r":70.976,"tau_r_min":1.0,"tau_r_max":3000.0,"tau_f":38.265,"tau_f_min":1.0,"tau_f_max":3000.0,"U":0.077,"U_min":0.001,"U_max":0.999,"error":0.221,"isCmOptimized":false,"isRinOptimized":false},{"Mode":"voltage-clamp","Erev":-83.24,"Vm":-11.34,"Rin":100.0,"Rin_min":10.0,"Rin_max":800.0,"Cm":100.0,"Cm_min":10.0,"Cm_max":1200.0,"g_syn":5.612,"g_syn_min":1.0,"g_syn_max":10.0,"tau_d":10.277,"tau_d_min":0.3,"tau_d_max":40.0,"tau_r":113.766,"tau_r_min":1.0,"tau_r_max":3000.0,"tau_f":32.716,"tau_f_min":1.0,"tau_f_max":3000.0,"U":0.027,"U_min":0.001,"U_max":0.999,"error":0.221,"isCmOptimized":false,"isRinOptimized":false},{"Mode":"voltage-clamp","Erev":-83.24,"Vm":-11.34,"Rin":100.0,"Rin_min":10.0,"Rin_max":800.0,"Cm":100.0,"Cm_min":10.0,"Cm_max":1200.0,"g_syn":5.422,"g_syn_min":1.0,"g_syn_max":10.0,"tau_d":10.232,"tau_d_min":0.3,"tau_d_max":40.0,"tau_r":103.706,"tau_r_min":1.0,"tau_r_max":3000.0,"tau_f":32.19,"tau_f_min":1.0,"tau_f_max":3000.0,"U":0.028,"U_min":0.001,"U_max":0.999,"error":0.221,"isCmOptimized":false,"isRinOptimized":false},{"Mode":"voltage-clamp","Erev":-83.24,"Vm":-11.34,"Rin":100.0,"Rin_min":10.0,"Rin_max":800.0,"Cm":100.0,"Cm_min":10.0,"Cm_max":1200.0,"g_syn":7.067,"g_syn_min":1.0,"g_syn_max":10.0,"tau_d":10.293,"tau_d_min":0.3,"tau_d_max":40.0,"tau_r":130.513,"tau_r_min":1.0,"tau_r_max":3000.0,"tau_f":31.892,"tau_f_min":1.0,"tau_f_max":3000.0,"U":0.022,"U_min":0.001,"U_max":0.999,"error":0.222,"isCmOptimized":false,"isRinOptimized":false},{"Mode":"voltage-clamp","Erev":-83.24,"Vm":-11.34,"Rin":100.0,"Rin_min":10.0,"Rin_max":800.0,"Cm":100.0,"Cm_min":10.0,"Cm_max":1200.0,"g_syn":7.094,"g_syn_min":1.0,"g_syn_max":10.0,"tau_d":10.259,"tau_d_min":0.3,"tau_d_max":40.0,"tau_r":112.758,"tau_r_min":1.0,"tau_r_max":3000.0,"tau_f":31.362,"tau_f_min":1.0,"tau_f_max":3000.0,"U":0.021,"U_min":0.001,"U_max":0.999,"error":0.221,"isCmOptimized":false,"isRinOptimized":false},{"Mode":"voltage-clamp","Erev":-83.24,"Vm":-11.34,"Rin":100.0,"Rin_min":10.0,"Rin_max":800.0,"Cm":100.0,"Cm_min":10.0,"Cm_max":1200.0,"g_syn":3.65,"g_syn_min":1.0,"g_syn_max":10.0,"tau_d":10.272,"tau_d_min":0.3,"tau_d_max":40.0,"tau_r":84.635,"tau_r_min":1.0,"tau_r_max":3000.0,"tau_f":33.554,"tau_f_min":1.0,"tau_f_max":3000.0,"U":0.042,"U_min":0.001,"U_max":0.999,"error":0.221,"isCmOptimized":false,"isRinOptimized":false},{"Mode":"voltage-clamp","Erev":-83.24,"Vm":-11.34,"Rin":100.0,"Rin_min":10.0,"Rin_max":800.0,"Cm":100.0,"Cm_min":10.0,"Cm_max":1200.0,"g_syn":1.309,"g_syn_min":1.0,"g_syn_max":10.0,"tau_d":10.259,"tau_d_min":0.3,"tau_d_max":40.0,"tau_r":62.431,"tau_r_min":1.0,"tau_r_max":3000.0,"tau_f":42.679,"tau_f_min":1.0,"tau_f_max":3000.0,"U":0.116,"U_min":0.001,"U_max":0.999,"error":0.221,"isCmOptimized":false,"isRinOptimized":false},{"Mode":"voltage-clamp","Erev":-83.24,"Vm":-11.34,"Rin":100.0,"Rin_min":10.0,"Rin_max":800.0,"Cm":100.0,"Cm_min":10.0,"Cm_max":1200.0,"g_syn":2.766,"g_syn_min":1.0,"g_syn_max":10.0,"tau_d":10.251,"tau_d_min":0.3,"tau_d_max":40.0,"tau_r":75.278,"tau_r_min":1.0,"tau_r_max":3000.0,"tau_f":35.17,"tau_f_min":1.0,"tau_f_max":3000.0,"U":0.055,"U_min":0.001,"U_max":0.999,"error":0.221,"isCmOptimized":false,"isRinOptimized":false},{"Mode":"voltage-clamp","Erev":-83.24,"Vm":-11.34,"Rin":100.0,"Rin_min":10.0,"Rin_max":800.0,"Cm":100.0,"Cm_min":10.0,"Cm_max":1200.0,"g_syn":1.168,"g_syn_min":1.0,"g_syn_max":10.0,"tau_d":10.263,"tau_d_min":0.3,"tau_d_max":40.0,"tau_r":57.657,"tau_r_min":1.0,"tau_r_max":3000.0,"tau_f":43.462,"tau_f_min":1.0,"tau_f_max":3000.0,"U":0.13,"U_min":0.001,"U_max":0.999,"error":0.221,"isCmOptimized":false,"isRinOptimized":false},{"Mode":"voltage-clamp","Erev":-83.24,"Vm":-11.34,"Rin":100.0,"Rin_min":10.0,"Rin_max":800.0,"Cm":100.0,"Cm_min":10.0,"Cm_max":1200.0,"g_syn":4.26,"g_syn_min":1.0,"g_syn_max":10.0,"tau_d":10.264,"tau_d_min":0.3,"tau_d_max":40.0,"tau_r":96.675,"tau_r_min":1.0,"tau_r_max":3000.0,"tau_f":33.386,"tau_f_min":1.0,"tau_f_max":3000.0,"U":0.036,"U_min":0.001,"U_max":0.999,"error":0.221,"isCmOptimized":false,"isRinOptimized":false},{"Mode":"voltage-clamp","Erev":-83.24,"Vm":-11.34,"Rin":100.0,"Rin_min":10.0,"Rin_max":800.0,"Cm":100.0,"Cm_min":10.0,"Cm_max":1200.0,"g_syn":3.07,"g_syn_min":1.0,"g_syn_max":10.0,"tau_d":10.276,"tau_d_min":0.3,"tau_d_max":40.0,"tau_r":78.893,"tau_r_min":1.0,"tau_r_max":3000.0,"tau_f":34.631,"tau_f_min":1.0,"tau_f_max":3000.0,"U":0.049,"U_min":0.001,"U_max":0.999,"error":0.221,"isCmOptimized":false,"isRinOptimized":false},{"Mode":"voltage-clamp","Erev":-83.24,"Vm":-11.34,"Rin":100.0,"Rin_min":10.0,"Rin_max":800.0,"Cm":100.0,"Cm_min":10.0,"Cm_max":1200.0,"g_syn":3.001,"g_syn_min":1.0,"g_syn_max":10.0,"tau_d":10.258,"tau_d_min":0.3,"tau_d_max":40.0,"tau_r":82.737,"tau_r_min":1.0,"tau_r_max":3000.0,"tau_f":35.048,"tau_f_min":1.0,"tau_f_max":3000.0,"U":0.051,"U_min":0.001,"U_max":0.999,"error":0.221,"isCmOptimized":false,"isRinOptimized":false},{"Mode":"voltage-clamp","Erev":-83.24,"Vm":-11.34,"Rin":100.0,"Rin_min":10.0,"Rin_max":800.0,"Cm":100.0,"Cm_min":10.0,"Cm_max":1200.0,"g_syn":2.649,"g_syn_min":1.0,"g_syn_max":10.0,"tau_d":10.218,"tau_d_min":0.3,"tau_d_max":40.0,"tau_r":77.605,"tau_r_min":1.0,"tau_r_max":3000.0,"tau_f":35.892,"tau_f_min":1.0,"tau_f_max":3000.0,"U":0.057,"U_min":0.001,"U_max":0.999,"error":0.221,"isCmOptimized":false,"isRinOptimized":false},{"Mode":"voltage-clamp","Erev":-83.24,"Vm":-11.34,"Rin":100.0,"Rin_min":10.0,"Rin_max":800.0,"Cm":100.0,"Cm_min":10.0,"Cm_max":1200.0,"g_syn":4.503,"g_syn_min":1.0,"g_syn_max":10.0,"tau_d":10.249,"tau_d_min":0.3,"tau_d_max":40.0,"tau_r":89.239,"tau_r_min":1.0,"tau_r_max":3000.0,"tau_f":32.685,"tau_f_min":1.0,"tau_f_max":3000.0,"U":0.034,"U_min":0.001,"U_max":0.999,"error":0.221,"isCmOptimized":false,"isRinOptimized":false},{"Mode":"voltage-clamp","Erev":-83.24,"Vm":-11.34,"Rin":100.0,"Rin_min":10.0,"Rin_max":800.0,"Cm":100.0,"Cm_min":10.0,"Cm_max":1200.0,"g_syn":4.326,"g_syn_min":1.0,"g_syn_max":10.0,"tau_d":10.252,"tau_d_min":0.3,"tau_d_max":40.0,"tau_r":89.691,"tau_r_min":1.0,"tau_r_max":3000.0,"tau_f":33.187,"tau_f_min":1.0,"tau_f_max":3000.0,"U":0.035,"U_min":0.001,"U_max":0.999,"error":0.221,"isCmOptimized":false,"isRinOptimized":false},{"Mode":"voltage-clamp","Erev":-83.24,"Vm":-11.34,"Rin":100.0,"Rin_min":10.0,"Rin_max":800.0,"Cm":100.0,"Cm_min":10.0,"Cm_max":1200.0,"g_syn":3.207,"g_syn_min":1.0,"g_syn_max":10.0,"tau_d":10.213,"tau_d_min":0.3,"tau_d_max":40.0,"tau_r":79.073,"tau_r_min":1.0,"tau_r_max":3000.0,"tau_f":34.165,"tau_f_min":1.0,"tau_f_max":3000.0,"U":0.047,"U_min":0.001,"U_max":0.999,"error":0.221,"isCmOptimized":false,"isRinOptimized":false},{"Mode":"voltage-clamp","Erev":-83.24,"Vm":-11.34,"Rin":100.0,"Rin_min":10.0,"Rin_max":800.0,"Cm":100.0,"Cm_min":10.0,"Cm_max":1200.0,"g_syn":2.724,"g_syn_min":1.0,"g_syn_max":10.0,"tau_d":10.26,"tau_d_min":0.3,"tau_d_max":40.0,"tau_r":73.406,"tau_r_min":1.0,"tau_r_max":3000.0,"tau_f":34.816,"tau_f_min":1.0,"tau_f_max":3000.0,"U":0.056,"U_min":0.001,"U_max":0.999,"error":0.221,"isCmOptimized":false,"isRinOptimized":false},{"Mode":"voltage-clamp","Erev":-83.24,"Vm":-11.34,"Rin":100.0,"Rin_min":10.0,"Rin_max":800.0,"Cm":100.0,"Cm_min":10.0,"Cm_max":1200.0,"g_syn":3.157,"g_syn_min":1.0,"g_syn_max":10.0,"tau_d":10.298,"tau_d_min":0.3,"tau_d_max":40.0,"tau_r":82.639,"tau_r_min":1.0,"tau_r_max":3000.0,"tau_f":34.612,"tau_f_min":1.0,"tau_f_max":3000.0,"U":0.048,"U_min":0.001,"U_max":0.999,"error":0.221,"isCmOptimized":false,"isRinOptimized":false},{"Mode":"voltage-clamp","Erev":-83.24,"Vm":-11.34,"Rin":100.0,"Rin_min":10.0,"Rin_max":800.0,"Cm":100.0,"Cm_min":10.0,"Cm_max":1200.0,"g_syn":1.184,"g_syn_min":1.0,"g_syn_max":10.0,"tau_d":10.268,"tau_d_min":0.3,"tau_d_max":40.0,"tau_r":60.56,"tau_r_min":1.0,"tau_r_max":3000.0,"tau_f":44.182,"tau_f_min":1.0,"tau_f_max":3000.0,"U":0.128,"U_min":0.001,"U_max":0.999,"error":0.221,"isCmOptimized":false,"isRinOptimized":false},{"Mode":"voltage-clamp","Erev":-83.24,"Vm":-11.34,"Rin":100.0,"Rin_min":10.0,"Rin_max":800.0,"Cm":100.0,"Cm_min":10.0,"Cm_max":1200.0,"g_syn":7.177,"g_syn_min":1.0,"g_syn_max":10.0,"tau_d":10.238,"tau_d_min":0.3,"tau_d_max":40.0,"tau_r":122.628,"tau_r_min":1.0,"tau_r_max":3000.0,"tau_f":31.695,"tau_f_min":1.0,"tau_f_max":3000.0,"U":0.021,"U_min":0.001,"U_max":0.999,"error":0.221,"isCmOptimized":false,"isRinOptimized":false},{"Mode":"voltage-clamp","Erev":-83.24,"Vm":-11.34,"Rin":100.0,"Rin_min":10.0,"Rin_max":800.0,"Cm":100.0,"Cm_min":10.0,"Cm_max":1200.0,"g_syn":7.973,"g_syn_min":1.0,"g_syn_max":10.0,"tau_d":10.283,"tau_d_min":0.3,"tau_d_max":40.0,"tau_r":130.678,"tau_r_min":1.0,"tau_r_max":3000.0,"tau_f":31.545,"tau_f_min":1.0,"tau_f_max":3000.0,"U":0.019,"U_min":0.001,"U_max":0.999,"error":0.221,"isCmOptimized":false,"isRinOptimized":false},{"Mode":"voltage-clamp","Erev":-83.24,"Vm":-11.34,"Rin":100.0,"Rin_min":10.0,"Rin_max":800.0,"Cm":100.0,"Cm_min":10.0,"Cm_max":1200.0,"g_syn":3.016,"g_syn_min":1.0,"g_syn_max":10.0,"tau_d":10.225,"tau_d_min":0.3,"tau_d_max":40.0,"tau_r":80.549,"tau_r_min":1.0,"tau_r_max":3000.0,"tau_f":34.712,"tau_f_min":1.0,"tau_f_max":3000.0,"U":0.05,"U_min":0.001,"U_max":0.999,"error":0.221,"isCmOptimized":false,"isRinOptimized":false},{"Mode":"voltage-clamp","Erev":-83.24,"Vm":-11.34,"Rin":100.0,"Rin_min":10.0,"Rin_max":800.0,"Cm":100.0,"Cm_min":10.0,"Cm_max":1200.0,"g_syn":4.022,"g_syn_min":1.0,"g_syn_max":10.0,"tau_d":10.269,"tau_d_min":0.3,"tau_d_max":40.0,"tau_r":91.8,"tau_r_min":1.0,"tau_r_max":3000.0,"tau_f":33.702,"tau_f_min":1.0,"tau_f_max":3000.0,"U":0.038,"U_min":0.001,"U_max":0.999,"error":0.221,"isCmOptimized":false,"isRinOptimized":false},{"Mode":"voltage-clamp","Erev":-83.24,"Vm":-11.34,"Rin":100.0,"Rin_min":10.0,"Rin_max":800.0,"Cm":100.0,"Cm_min":10.0,"Cm_max":1200.0,"g_syn":8.608,"g_syn_min":1.0,"g_syn_max":10.0,"tau_d":10.237,"tau_d_min":0.3,"tau_d_max":40.0,"tau_r":143.131,"tau_r_min":1.0,"tau_r_max":3000.0,"tau_f":31.747,"tau_f_min":1.0,"tau_f_max":3000.0,"U":0.018,"U_min":0.001,"U_max":0.999,"error":0.222,"isCmOptimized":false,"isRinOptimized":false},{"Mode":"voltage-clamp","Erev":-83.24,"Vm":-11.34,"Rin":100.0,"Rin_min":10.0,"Rin_max":800.0,"Cm":100.0,"Cm_min":10.0,"Cm_max":1200.0,"g_syn":2.274,"g_syn_min":1.0,"g_syn_max":10.0,"tau_d":10.271,"tau_d_min":0.3,"tau_d_max":40.0,"tau_r":73.144,"tau_r_min":1.0,"tau_r_max":3000.0,"tau_f":36.69,"tau_f_min":1.0,"tau_f_max":3000.0,"U":0.067,"U_min":0.001,"U_max":0.999,"error":0.221,"isCmOptimized":false,"isRinOptimized":false},{"Mode":"voltage-clamp","Erev":-83.24,"Vm":-11.34,"Rin":100.0,"Rin_min":10.0,"Rin_max":800.0,"Cm":100.0,"Cm_min":10.0,"Cm_max":1200.0,"g_syn":2.02,"g_syn_min":1.0,"g_syn_max":10.0,"tau_d":10.241,"tau_d_min":0.3,"tau_d_max":40.0,"tau_r":71.653,"tau_r_min":1.0,"tau_r_max":3000.0,"tau_f":37.686,"tau_f_min":1.0,"tau_f_max":3000.0,"U":0.075,"U_min":0.001,"U_max":0.999,"error":0.221,"isCmOptimized":false,"isRinOptimized":false},{"Mode":"voltage-clamp","Erev":-83.24,"Vm":-11.34,"Rin":100.0,"Rin_min":10.0,"Rin_max":800.0,"Cm":100.0,"Cm_min":10.0,"Cm_max":1200.0,"g_syn":3.64,"g_syn_min":1.0,"g_syn_max":10.0,"tau_d":10.24,"tau_d_min":0.3,"tau_d_max":40.0,"tau_r":89.672,"tau_r_min":1.0,"tau_r_max":3000.0,"tau_f":34.237,"tau_f_min":1.0,"tau_f_max":3000.0,"U":0.042,"U_min":0.001,"U_max":0.999,"error":0.221,"isCmOptimized":false,"isRinOptimized":false},{"Mode":"voltage-clamp","Erev":-83.24,"Vm":-11.34,"Rin":100.0,"Rin_min":10.0,"Rin_max":800.0,"Cm":100.0,"Cm_min":10.0,"Cm_max":1200.0,"g_syn":7.25,"g_syn_min":1.0,"g_syn_max":10.0,"tau_d":10.251,"tau_d_min":0.3,"tau_d_max":40.0,"tau_r":124.736,"tau_r_min":1.0,"tau_r_max":3000.0,"tau_f":31.809,"tau_f_min":1.0,"tau_f_max":3000.0,"U":0.021,"U_min":0.001,"U_max":0.999,"error":0.221,"isCmOptimized":false,"isRinOptimized":false},{"Mode":"voltage-clamp","Erev":-83.24,"Vm":-11.34,"Rin":100.0,"Rin_min":10.0,"Rin_max":800.0,"Cm":100.0,"Cm_min":10.0,"Cm_max":1200.0,"g_syn":9.619,"g_syn_min":1.0,"g_syn_max":10.0,"tau_d":10.23,"tau_d_min":0.3,"tau_d_max":40.0,"tau_r":155.068,"tau_r_min":1.0,"tau_r_max":3000.0,"tau_f":31.279,"tau_f_min":1.0,"tau_f_max":3000.0,"U":0.016,"U_min":0.001,"U_max":0.999,"error":0.222,"isCmOptimized":false,"isRinOptimized":false},{"Mode":"voltage-clamp","Erev":-83.24,"Vm":-11.34,"Rin":100.0,"Rin_min":10.0,"Rin_max":800.0,"Cm":100.0,"Cm_min":10.0,"Cm_max":1200.0,"g_syn":5.9,"g_syn_min":1.0,"g_syn_max":10.0,"tau_d":10.259,"tau_d_min":0.3,"tau_d_max":40.0,"tau_r":113.215,"tau_r_min":1.0,"tau_r_max":3000.0,"tau_f":32.398,"tau_f_min":1.0,"tau_f_max":3000.0,"U":0.026,"U_min":0.001,"U_max":0.999,"error":0.221,"isCmOptimized":false,"isRinOptimized":false},{"Mode":"voltage-clamp","Erev":-83.24,"Vm":-11.34,"Rin":100.0,"Rin_min":10.0,"Rin_max":800.0,"Cm":100.0,"Cm_min":10.0,"Cm_max":1200.0,"g_syn":5.819,"g_syn_min":1.0,"g_syn_max":10.0,"tau_d":10.278,"tau_d_min":0.3,"tau_d_max":40.0,"tau_r":109.465,"tau_r_min":1.0,"tau_r_max":3000.0,"tau_f":32.213,"tau_f_min":1.0,"tau_f_max":3000.0,"U":0.026,"U_min":0.001,"U_max":0.999,"error":0.221,"isCmOptimized":false,"isRinOptimized":false},{"Mode":"voltage-clamp","Erev":-83.24,"Vm":-11.34,"Rin":100.0,"Rin_min":10.0,"Rin_max":800.0,"Cm":100.0,"Cm_min":10.0,"Cm_max":1200.0,"g_syn":7.877,"g_syn_min":1.0,"g_syn_max":10.0,"tau_d":10.271,"tau_d_min":0.3,"tau_d_max":40.0,"tau_r":123.534,"tau_r_min":1.0,"tau_r_max":3000.0,"tau_f":31.195,"tau_f_min":1.0,"tau_f_max":3000.0,"U":0.019,"U_min":0.001,"U_max":0.999,"error":0.221,"isCmOptimized":false,"isRinOptimized":false},{"Mode":"voltage-clamp","Erev":-83.24,"Vm":-11.34,"Rin":100.0,"Rin_min":10.0,"Rin_max":800.0,"Cm":100.0,"Cm_min":10.0,"Cm_max":1200.0,"g_syn":4.774,"g_syn_min":1.0,"g_syn_max":10.0,"tau_d":10.274,"tau_d_min":0.3,"tau_d_max":40.0,"tau_r":92.561,"tau_r_min":1.0,"tau_r_max":3000.0,"tau_f":32.774,"tau_f_min":1.0,"tau_f_max":3000.0,"U":0.032,"U_min":0.001,"U_max":0.999,"error":0.221,"isCmOptimized":false,"isRinOptimized":false},{"Mode":"voltage-clamp","Erev":-83.24,"Vm":-11.34,"Rin":100.0,"Rin_min":10.0,"Rin_max":800.0,"Cm":100.0,"Cm_min":10.0,"Cm_max":1200.0,"g_syn":7.188,"g_syn_min":1.0,"g_syn_max":10.0,"tau_d":10.265,"tau_d_min":0.3,"tau_d_max":40.0,"tau_r":124.491,"tau_r_min":1.0,"tau_r_max":3000.0,"tau_f":31.82,"tau_f_min":1.0,"tau_f_max":3000.0,"U":0.021,"U_min":0.001,"U_max":0.999,"error":0.221,"isCmOptimized":false,"isRinOptimized":false},{"Mode":"voltage-clamp","Erev":-83.24,"Vm":-11.34,"Rin":100.0,"Rin_min":10.0,"Rin_max":800.0,"Cm":100.0,"Cm_min":10.0,"Cm_max":1200.0,"g_syn":6.823,"g_syn_min":1.0,"g_syn_max":10.0,"tau_d":10.267,"tau_d_min":0.3,"tau_d_max":40.0,"tau_r":117.253,"tau_r_min":1.0,"tau_r_max":3000.0,"tau_f":31.79,"tau_f_min":1.0,"tau_f_max":3000.0,"U":0.022,"U_min":0.001,"U_max":0.999,"error":0.221,"isCmOptimized":false,"isRinOptimized":false},{"Mode":"voltage-clamp","Erev":-83.24,"Vm":-11.34,"Rin":100.0,"Rin_min":10.0,"Rin_max":800.0,"Cm":100.0,"Cm_min":10.0,"Cm_max":1200.0,"g_syn":3.133,"g_syn_min":1.0,"g_syn_max":10.0,"tau_d":10.266,"tau_d_min":0.3,"tau_d_max":40.0,"tau_r":81.677,"tau_r_min":1.0,"tau_r_max":3000.0,"tau_f":34.478,"tau_f_min":1.0,"tau_f_max":3000.0,"U":0.049,"U_min":0.001,"U_max":0.999,"error":0.221,"isCmOptimized":false,"isRinOptimized":false},{"Mode":"voltage-clamp","Erev":-83.24,"Vm":-11.34,"Rin":100.0,"Rin_min":10.0,"Rin_max":800.0,"Cm":100.0,"Cm_min":10.0,"Cm_max":1200.0,"g_syn":1.082,"g_syn_min":1.0,"g_syn_max":10.0,"tau_d":10.262,"tau_d_min":0.3,"tau_d_max":40.0,"tau_r":57.083,"tau_r_min":1.0,"tau_r_max":3000.0,"tau_f":45.0,"tau_f_min":1.0,"tau_f_max":3000.0,"U":0.14,"U_min":0.001,"U_max":0.999,"error":0.221,"isCmOptimized":false,"isRinOptimized":false},{"Mode":"voltage-clamp","Erev":-83.24,"Vm":-11.34,"Rin":100.0,"Rin_min":10.0,"Rin_max":800.0,"Cm":100.0,"Cm_min":10.0,"Cm_max":1200.0,"g_syn":3.974,"g_syn_min":1.0,"g_syn_max":10.0,"tau_d":10.316,"tau_d_min":0.3,"tau_d_max":40.0,"tau_r":86.297,"tau_r_min":1.0,"tau_r_max":3000.0,"tau_f":33.33,"tau_f_min":1.0,"tau_f_max":3000.0,"U":0.038,"U_min":0.001,"U_max":0.999,"error":0.221,"isCmOptimized":false,"isRinOptimized":false},{"Mode":"voltage-clamp","Erev":-83.24,"Vm":-11.34,"Rin":100.0,"Rin_min":10.0,"Rin_max":800.0,"Cm":100.0,"Cm_min":10.0,"Cm_max":1200.0,"g_syn":4.924,"g_syn_min":1.0,"g_syn_max":10.0,"tau_d":10.249,"tau_d_min":0.3,"tau_d_max":40.0,"tau_r":98.281,"tau_r_min":1.0,"tau_r_max":3000.0,"tau_f":32.6,"tau_f_min":1.0,"tau_f_max":3000.0,"U":0.031,"U_min":0.001,"U_max":0.999,"error":0.221,"isCmOptimized":false,"isRinOptimized":false},{"Mode":"voltage-clamp","Erev":-83.24,"Vm":-11.34,"Rin":100.0,"Rin_min":10.0,"Rin_max":800.0,"Cm":100.0,"Cm_min":10.0,"Cm_max":1200.0,"g_syn":2.218,"g_syn_min":1.0,"g_syn_max":10.0,"tau_d":10.258,"tau_d_min":0.3,"tau_d_max":40.0,"tau_r":69.212,"tau_r_min":1.0,"tau_r_max":3000.0,"tau_f":36.567,"tau_f_min":1.0,"tau_f_max":3000.0,"U":0.068,"U_min":0.001,"U_max":0.999,"error":0.221,"isCmOptimized":false,"isRinOptimized":false},{"Mode":"voltage-clamp","Erev":-83.24,"Vm":-11.34,"Rin":100.0,"Rin_min":10.0,"Rin_max":800.0,"Cm":100.0,"Cm_min":10.0,"Cm_max":1200.0,"g_syn":1.289,"g_syn_min":1.0,"g_syn_max":10.0,"tau_d":10.256,"tau_d_min":0.3,"tau_d_max":40.0,"tau_r":58.561,"tau_r_min":1.0,"tau_r_max":3000.0,"tau_f":41.775,"tau_f_min":1.0,"tau_f_max":3000.0,"U":0.118,"U_min":0.001,"U_max":0.999,"error":0.221,"isCmOptimized":false,"isRinOptimized":false},{"Mode":"voltage-clamp","Erev":-83.24,"Vm":-11.34,"Rin":100.0,"Rin_min":10.0,"Rin_max":800.0,"Cm":100.0,"Cm_min":10.0,"Cm_max":1200.0,"g_syn":7.864,"g_syn_min":1.0,"g_syn_max":10.0,"tau_d":10.257,"tau_d_min":0.3,"tau_d_max":40.0,"tau_r":129.429,"tau_r_min":1.0,"tau_r_max":3000.0,"tau_f":31.558,"tau_f_min":1.0,"tau_f_max":3000.0,"U":0.019,"U_min":0.001,"U_max":0.999,"error":0.221,"isCmOptimized":false,"isRinOptimized":false},{"Mode":"voltage-clamp","Erev":-83.24,"Vm":-11.34,"Rin":100.0,"Rin_min":10.0,"Rin_max":800.0,"Cm":100.0,"Cm_min":10.0,"Cm_max":1200.0,"g_syn":7.61,"g_syn_min":1.0,"g_syn_max":10.0,"tau_d":10.265,"tau_d_min":0.3,"tau_d_max":40.0,"tau_r":119.171,"tau_r_min":1.0,"tau_r_max":3000.0,"tau_f":31.283,"tau_f_min":1.0,"tau_f_max":3000.0,"U":0.02,"U_min":0.001,"U_max":0.999,"error":0.221,"isCmOptimized":false,"isRinOptimized":false},{"Mode":"voltage-clamp","Erev":-83.24,"Vm":-11.34,"Rin":100.0,"Rin_min":10.0,"Rin_max":800.0,"Cm":100.0,"Cm_min":10.0,"Cm_max":1200.0,"g_syn":3.524,"g_syn_min":1.0,"g_syn_max":10.0,"tau_d":10.274,"tau_d_min":0.3,"tau_d_max":40.0,"tau_r":89.664,"tau_r_min":1.0,"tau_r_max":3000.0,"tau_f":34.439,"tau_f_min":1.0,"tau_f_max":3000.0,"U":0.043,"U_min":0.001,"U_max":0.999,"error":0.221,"isCmOptimized":false,"isRinOptimized":false},{"Mode":"voltage-clamp","Erev":-83.24,"Vm":-11.34,"Rin":100.0,"Rin_min":10.0,"Rin_max":800.0,"Cm":100.0,"Cm_min":10.0,"Cm_max":1200.0,"g_syn":1.849,"g_syn_min":1.0,"g_syn_max":10.0,"tau_d":10.291,"tau_d_min":0.3,"tau_d_max":40.0,"tau_r":65.16,"tau_r_min":1.0,"tau_r_max":3000.0,"tau_f":37.805,"tau_f_min":1.0,"tau_f_max":3000.0,"U":0.082,"U_min":0.001,"U_max":0.999,"error":0.221,"isCmOptimized":false,"isRinOptimized":false},{"Mode":"voltage-clamp","Erev":-83.24,"Vm":-11.34,"Rin":100.0,"Rin_min":10.0,"Rin_max":800.0,"Cm":100.0,"Cm_min":10.0,"Cm_max":1200.0,"g_syn":5.095,"g_syn_min":1.0,"g_syn_max":10.0,"tau_d":10.256,"tau_d_min":0.3,"tau_d_max":40.0,"tau_r":101.73,"tau_r_min":1.0,"tau_r_max":3000.0,"tau_f":32.744,"tau_f_min":1.0,"tau_f_max":3000.0,"U":0.03,"U_min":0.001,"U_max":0.999,"error":0.221,"isCmOptimized":false,"isRinOptimized":false},{"Mode":"voltage-clamp","Erev":-83.24,"Vm":-11.34,"Rin":100.0,"Rin_min":10.0,"Rin_max":800.0,"Cm":100.0,"Cm_min":10.0,"Cm_max":1200.0,"g_syn":5.186,"g_syn_min":1.0,"g_syn_max":10.0,"tau_d":10.256,"tau_d_min":0.3,"tau_d_max":40.0,"tau_r":98.662,"tau_r_min":1.0,"tau_r_max":3000.0,"tau_f":32.282,"tau_f_min":1.0,"tau_f_max":3000.0,"U":0.029,"U_min":0.001,"U_max":0.999,"error":0.221,"isCmOptimized":false,"isRinOptimized":false},{"Mode":"voltage-clamp","Erev":-83.24,"Vm":-11.34,"Rin":100.0,"Rin_min":10.0,"Rin_max":800.0,"Cm":100.0,"Cm_min":10.0,"Cm_max":1200.0,"g_syn":6.292,"g_syn_min":1.0,"g_syn_max":10.0,"tau_d":10.251,"tau_d_min":0.3,"tau_d_max":40.0,"tau_r":118.189,"tau_r_min":1.0,"tau_r_max":3000.0,"tau_f":32.336,"tau_f_min":1.0,"tau_f_max":3000.0,"U":0.024,"U_min":0.001,"U_max":0.999,"error":0.221,"isCmOptimized":false,"isRinOptimized":false}]