[{"Mode":"current-clamp","Erev":-8.49,"Vm":-66.17,"Rin":32.9,"Rin_min":10.0,"Rin_max":400.0,"Cm":227.96,"Cm_min":10.0,"Cm_max":400.0,"g_syn":0.467,"g_syn_min":0.1,"g_syn_max":8.0,"tau_d":15.279,"tau_d_min":1.0,"tau_d_max":30.0,"tau_r":971.963,"tau_r_min":1.0,"tau_r_max":1000.0,"tau_f":321.987,"tau_f_min":10.0,"tau_f_max":1000.0,"U":0.999,"U_min":0.2,"U_max":0.999,"error":11.272,"isCmOptimized":false,"isRinOptimized":false},{"Mode":"current-clamp","Erev":-8.49,"Vm":-66.17,"Rin":32.9,"Rin_min":10.0,"Rin_max":400.0,"Cm":227.96,"Cm_min":10.0,"Cm_max":400.0,"g_syn":0.469,"g_syn_min":0.1,"g_syn_max":8.0,"tau_d":15.108,"tau_d_min":1.0,"tau_d_max":30.0,"tau_r":37.032,"tau_r_min":1.0,"tau_r_max":1000.0,"tau_f":758.481,"tau_f_min":10.0,"tau_f_max":1000.0,"U":0.999,"U_min":0.2,"U_max":0.999,"error":11.272,"isCmOptimized":false,"isRinOptimized":false},{"Mode":"current-clamp","Erev":-8.49,"Vm":-66.17,"Rin":32.9,"Rin_min":10.0,"Rin_max":400.0,"Cm":227.96,"Cm_min":10.0,"Cm_max":400.0,"g_syn":0.464,"g_syn_min":0.1,"g_syn_max":8.0,"tau_d":15.461,"tau_d_min":1.0,"tau_d_max":30.0,"tau_r":727.885,"tau_r_min":1.0,"tau_r_max":1000.0,"tau_f":60.699,"tau_f_min":10.0,"tau_f_max":1000.0,"U":0.999,"U_min":0.2,"U_max":0.999,"error":11.272,"isCmOptimized":false,"isRinOptimized":false},{"Mode":"current-clamp","Erev":-8.49,"Vm":-66.17,"Rin":32.9,"Rin_min":10.0,"Rin_max":400.0,"Cm":227.96,"Cm_min":10.0,"Cm_max":400.0,"g_syn":0.465,"g_syn_min":0.1,"g_syn_max":8.0,"tau_d":15.372,"tau_d_min":1.0,"tau_d_max":30.0,"tau_r":279.153,"tau_r_min":1.0,"tau_r_max":1000.0,"tau_f":127.765,"tau_f_min":10.0,"tau_f_max":1000.0,"U":0.999,"U_min":0.2,"U_max":0.999,"error":11.272,"isCmOptimized":false,"isRinOptimized":false},{"Mode":"current-clamp","Erev":-8.49,"Vm":-66.17,"Rin":32.9,"Rin_min":10.0,"Rin_max":400.0,"Cm":227.96,"Cm_min":10.0,"Cm_max":400.0,"g_syn":0.446,"g_syn_min":0.1,"g_syn_max":8.0,"tau_d":16.188,"tau_d_min":1.0,"tau_d_max":30.0,"tau_r":240.92,"tau_r_min":1.0,"tau_r_max":1000.0,"tau_f":754.611,"tau_f_min":10.0,"tau_f_max":1000.0,"U":0.999,"U_min":0.2,"U_max":0.999,"error":11.273,"isCmOptimized":false,"isRinOptimized":false},{"Mode":"current-clamp","Erev":-8.49,"Vm":-66.17,"Rin":32.9,"Rin_min":10.0,"Rin_max":400.0,"Cm":227.96,"Cm_min":10.0,"Cm_max":400.0,"g_syn":0.464,"g_syn_min":0.1,"g_syn_max":8.0,"tau_d":15.441,"tau_d_min":1.0,"tau_d_max":30.0,"tau_r":903.752,"tau_r_min":1.0,"tau_r_max":1000.0,"tau_f":894.436,"tau_f_min":10.0,"tau_f_max":1000.0,"U":0.999,"U_min":0.2,"U_max":0.999,"error":11.272,"isCmOptimized":false,"isRinOptimized":false},{"Mode":"current-clamp","Erev":-8.49,"Vm":-66.17,"Rin":32.9,"Rin_min":10.0,"Rin_max":400.0,"Cm":227.96,"Cm_min":10.0,"Cm_max":400.0,"g_syn":0.462,"g_syn_min":0.1,"g_syn_max":8.0,"tau_d":15.598,"tau_d_min":1.0,"tau_d_max":30.0,"tau_r":203.112,"tau_r_min":1.0,"tau_r_max":1000.0,"tau_f":244.149,"tau_f_min":10.0,"tau_f_max":1000.0,"U":0.999,"U_min":0.2,"U_max":0.999,"error":11.272,"isCmOptimized":false,"isRinOptimized":false},{"Mode":"current-clamp","Erev":-8.49,"Vm":-66.17,"Rin":32.9,"Rin_min":10.0,"Rin_max":400.0,"Cm":227.96,"Cm_min":10.0,"Cm_max":400.0,"g_syn":0.478,"g_syn_min":0.1,"g_syn_max":8.0,"tau_d":14.47,"tau_d_min":1.0,"tau_d_max":30.0,"tau_r":745.668,"tau_r_min":1.0,"tau_r_max":1000.0,"tau_f":24.714,"tau_f_min":10.0,"tau_f_max":1000.0,"U":0.999,"U_min":0.2,"U_max":0.999,"error":11.272,"isCmOptimized":false,"isRinOptimized":false},{"Mode":"current-clamp","Erev":-8.49,"Vm":-66.17,"Rin":32.9,"Rin_min":10.0,"Rin_max":400.0,"Cm":227.96,"Cm_min":10.0,"Cm_max":400.0,"g_syn":0.458,"g_syn_min":0.1,"g_syn_max":8.0,"tau_d":15.973,"tau_d_min":1.0,"tau_d_max":30.0,"tau_r":862.514,"tau_r_min":1.0,"tau_r_max":1000.0,"tau_f":954.458,"tau_f_min":10.0,"tau_f_max":1000.0,"U":0.999,"U_min":0.2,"U_max":0.999,"error":11.272,"isCmOptimized":false,"isRinOptimized":false},{"Mode":"current-clamp","Erev":-8.49,"Vm":-66.17,"Rin":32.9,"Rin_min":10.0,"Rin_max":400.0,"Cm":227.96,"Cm_min":10.0,"Cm_max":400.0,"g_syn":0.457,"g_syn_min":0.1,"g_syn_max":8.0,"tau_d":15.759,"tau_d_min":1.0,"tau_d_max":30.0,"tau_r":236.129,"tau_r_min":1.0,"tau_r_max":1000.0,"tau_f":256.77,"tau_f_min":10.0,"tau_f_max":1000.0,"U":0.999,"U_min":0.2,"U_max":0.999,"error":11.272,"isCmOptimized":false,"isRinOptimized":false},{"Mode":"current-clamp","Erev":-8.49,"Vm":-66.17,"Rin":32.9,"Rin_min":10.0,"Rin_max":400.0,"Cm":227.96,"Cm_min":10.0,"Cm_max":400.0,"g_syn":0.458,"g_syn_min":0.1,"g_syn_max":8.0,"tau_d":15.952,"tau_d_min":1.0,"tau_d_max":30.0,"tau_r":827.473,"tau_r_min":1.0,"tau_r_max":1000.0,"tau_f":53.307,"tau_f_min":10.0,"tau_f_max":1000.0,"U":0.999,"U_min":0.2,"U_max":0.999,"error":11.272,"isCmOptimized":false,"isRinOptimized":false},{"Mode":"current-clamp","Erev":-8.49,"Vm":-66.17,"Rin":32.9,"Rin_min":10.0,"Rin_max":400.0,"Cm":227.96,"Cm_min":10.0,"Cm_max":400.0,"g_syn":0.468,"g_syn_min":0.1,"g_syn_max":8.0,"tau_d":15.15,"tau_d_min":1.0,"tau_d_max":30.0,"tau_r":938.156,"tau_r_min":1.0,"tau_r_max":1000.0,"tau_f":300.174,"tau_f_min":10.0,"tau_f_max":1000.0,"U":0.999,"U_min":0.2,"U_max":0.999,"error":11.272,"isCmOptimized":false,"isRinOptimized":false},{"Mode":"current-clamp","Erev":-8.49,"Vm":-66.17,"Rin":32.9,"Rin_min":10.0,"Rin_max":400.0,"Cm":227.96,"Cm_min":10.0,"Cm_max":400.0,"g_syn":0.483,"g_syn_min":0.1,"g_syn_max":8.0,"tau_d":14.135,"tau_d_min":1.0,"tau_d_max":30.0,"tau_r":870.262,"tau_r_min":1.0,"tau_r_max":1000.0,"tau_f":643.655,"tau_f_min":10.0,"tau_f_max":1000.0,"U":0.999,"U_min":0.2,"U_max":0.999,"error":11.273,"isCmOptimized":false,"isRinOptimized":false},{"Mode":"current-clamp","Erev":-8.49,"Vm":-66.17,"Rin":32.9,"Rin_min":10.0,"Rin_max":400.0,"Cm":227.96,"Cm_min":10.0,"Cm_max":400.0,"g_syn":0.472,"g_syn_min":0.1,"g_syn_max":8.0,"tau_d":14.957,"tau_d_min":1.0,"tau_d_max":30.0,"tau_r":354.143,"tau_r_min":1.0,"tau_r_max":1000.0,"tau_f":893.395,"tau_f_min":10.0,"tau_f_max":1000.0,"U":0.999,"U_min":0.2,"U_max":0.999,"error":11.272,"isCmOptimized":false,"isRinOptimized":false},{"Mode":"current-clamp","Erev":-8.49,"Vm":-66.17,"Rin":32.9,"Rin_min":10.0,"Rin_max":400.0,"Cm":227.96,"Cm_min":10.0,"Cm_max":400.0,"g_syn":0.465,"g_syn_min":0.1,"g_syn_max":8.0,"tau_d":15.374,"tau_d_min":1.0,"tau_d_max":30.0,"tau_r":861.223,"tau_r_min":1.0,"tau_r_max":1000.0,"tau_f":685.802,"tau_f_min":10.0,"tau_f_max":1000.0,"U":0.999,"U_min":0.2,"U_max":0.999,"error":11.272,"isCmOptimized":false,"isRinOptimized":false},{"Mode":"current-clamp","Erev":-8.49,"Vm":-66.17,"Rin":32.9,"Rin_min":10.0,"Rin_max":400.0,"Cm":227.96,"Cm_min":10.0,"Cm_max":400.0,"g_syn":0.465,"g_syn_min":0.1,"g_syn_max":8.0,"tau_d":15.313,"tau_d_min":1.0,"tau_d_max":30.0,"tau_r":255.853,"tau_r_min":1.0,"tau_r_max":1000.0,"tau_f":394.477,"tau_f_min":10.0,"tau_f_max":1000.0,"U":0.999,"U_min":0.2,"U_max":0.999,"error":11.272,"isCmOptimized":false,"isRinOptimized":false},{"Mode":"current-clamp","Erev":-8.49,"Vm":-66.17,"Rin":32.9,"Rin_min":10.0,"Rin_max":400.0,"Cm":227.96,"Cm_min":10.0,"Cm_max":400.0,"g_syn":0.476,"g_syn_min":0.1,"g_syn_max":8.0,"tau_d":14.59,"tau_d_min":1.0,"tau_d_max":30.0,"tau_r":683.463,"tau_r_min":1.0,"tau_r_max":1000.0,"tau_f":36.844,"tau_f_min":10.0,"tau_f_max":1000.0,"U":0.999,"U_min":0.2,"U_max":0.999,"error":11.272,"isCmOptimized":false,"isRinOptimized":false},{"Mode":"current-clamp","Erev":-8.49,"Vm":-66.17,"Rin":32.9,"Rin_min":10.0,"Rin_max":400.0,"Cm":227.96,"Cm_min":10.0,"Cm_max":400.0,"g_syn":0.454,"g_syn_min":0.1,"g_syn_max":8.0,"tau_d":16.197,"tau_d_min":1.0,"tau_d_max":30.0,"tau_r":642.979,"tau_r_min":1.0,"tau_r_max":1000.0,"tau_f":608.302,"tau_f_min":10.0,"tau_f_max":1000.0,"U":0.999,"U_min":0.2,"U_max":0.999,"error":11.272,"isCmOptimized":false,"isRinOptimized":false},{"Mode":"current-clamp","Erev":-8.49,"Vm":-66.17,"Rin":32.9,"Rin_min":10.0,"Rin_max":400.0,"Cm":227.96,"Cm_min":10.0,"Cm_max":400.0,"g_syn":0.457,"g_syn_min":0.1,"g_syn_max":8.0,"tau_d":15.964,"tau_d_min":1.0,"tau_d_max":30.0,"tau_r":446.981,"tau_r_min":1.0,"tau_r_max":1000.0,"tau_f":317.901,"tau_f_min":10.0,"tau_f_max":1000.0,"U":0.999,"U_min":0.2,"U_max":0.999,"error":11.272,"isCmOptimized":false,"isRinOptimized":false},{"Mode":"current-clamp","Erev":-8.49,"Vm":-66.17,"Rin":32.9,"Rin_min":10.0,"Rin_max":400.0,"Cm":227.96,"Cm_min":10.0,"Cm_max":400.0,"g_syn":0.44,"g_syn_min":0.1,"g_syn_max":8.0,"tau_d":17.376,"tau_d_min":1.0,"tau_d_max":30.0,"tau_r":144.364,"tau_r_min":1.0,"tau_r_max":1000.0,"tau_f":411.733,"tau_f_min":10.0,"tau_f_max":1000.0,"U":0.999,"U_min":0.2,"U_max":0.999,"error":11.274,"isCmOptimized":false,"isRinOptimized":false},{"Mode":"current-clamp","Erev":-8.49,"Vm":-66.17,"Rin":32.9,"Rin_min":10.0,"Rin_max":400.0,"Cm":227.96,"Cm_min":10.0,"Cm_max":400.0,"g_syn":0.453,"g_syn_min":0.1,"g_syn_max":8.0,"tau_d":16.308,"tau_d_min":1.0,"tau_d_max":30.0,"tau_r":807.189,"tau_r_min":1.0,"tau_r_max":1000.0,"tau_f":476.79,"tau_f_min":10.0,"tau_f_max":1000.0,"U":0.999,"U_min":0.2,"U_max":0.999,"error":11.273,"isCmOptimized":false,"isRinOptimized":false},{"Mode":"current-clamp","Erev":-8.49,"Vm":-66.17,"Rin":32.9,"Rin_min":10.0,"Rin_max":400.0,"Cm":227.96,"Cm_min":10.0,"Cm_max":400.0,"g_syn":0.454,"g_syn_min":0.1,"g_syn_max":8.0,"tau_d":16.29,"tau_d_min":1.0,"tau_d_max":30.0,"tau_r":279.838,"tau_r_min":1.0,"tau_r_max":1000.0,"tau_f":543.38,"tau_f_min":10.0,"tau_f_max":1000.0,"U":0.999,"U_min":0.2,"U_max":0.999,"error":11.273,"isCmOptimized":false,"isRinOptimized":false},{"Mode":"current-clamp","Erev":-8.49,"Vm":-66.17,"Rin":32.9,"Rin_min":10.0,"Rin_max":400.0,"Cm":227.96,"Cm_min":10.0,"Cm_max":400.0,"g_syn":0.469,"g_syn_min":0.1,"g_syn_max":8.0,"tau_d":15.176,"tau_d_min":1.0,"tau_d_max":30.0,"tau_r":651.838,"tau_r_min":1.0,"tau_r_max":1000.0,"tau_f":660.419,"tau_f_min":10.0,"tau_f_max":1000.0,"U":0.999,"U_min":0.2,"U_max":0.999,"error":11.272,"isCmOptimized":false,"isRinOptimized":false},{"Mode":"current-clamp","Erev":-8.49,"Vm":-66.17,"Rin":32.9,"Rin_min":10.0,"Rin_max":400.0,"Cm":227.96,"Cm_min":10.0,"Cm_max":400.0,"g_syn":0.463,"g_syn_min":0.1,"g_syn_max":8.0,"tau_d":15.601,"tau_d_min":1.0,"tau_d_max":30.0,"tau_r":133.433,"tau_r_min":1.0,"tau_r_max":1000.0,"tau_f":569.242,"tau_f_min":10.0,"tau_f_max":1000.0,"U":0.999,"U_min":0.2,"U_max":0.999,"error":11.272,"isCmOptimized":false,"isRinOptimized":false},{"Mode":"current-clamp","Erev":-8.49,"Vm":-66.17,"Rin":32.9,"Rin_min":10.0,"Rin_max":400.0,"Cm":227.96,"Cm_min":10.0,"Cm_max":400.0,"g_syn":0.47,"g_syn_min":0.1,"g_syn_max":8.0,"tau_d":15.001,"tau_d_min":1.0,"tau_d_max":30.0,"tau_r":618.492,"tau_r_min":1.0,"tau_r_max":1000.0,"tau_f":120.338,"tau_f_min":10.0,"tau_f_max":1000.0,"U":0.999,"U_min":0.2,"U_max":0.999,"error":11.272,"isCmOptimized":false,"isRinOptimized":false},{"Mode":"current-clamp","Erev":-8.49,"Vm":-66.17,"Rin":32.9,"Rin_min":10.0,"Rin_max":400.0,"Cm":227.96,"Cm_min":10.0,"Cm_max":400.0,"g_syn":0.461,"g_syn_min":0.1,"g_syn_max":8.0,"tau_d":15.684,"tau_d_min":1.0,"tau_d_max":30.0,"tau_r":433.438,"tau_r_min":1.0,"tau_r_max":1000.0,"tau_f":19.197,"tau_f_min":10.0,"tau_f_max":1000.0,"U":0.999,"U_min":0.2,"U_max":0.999,"error":11.272,"isCmOptimized":false,"isRinOptimized":false},{"Mode":"current-clamp","Erev":-8.49,"Vm":-66.17,"Rin":32.9,"Rin_min":10.0,"Rin_max":400.0,"Cm":227.96,"Cm_min":10.0,"Cm_max":400.0,"g_syn":0.466,"g_syn_min":0.1,"g_syn_max":8.0,"tau_d":15.292,"tau_d_min":1.0,"tau_d_max":30.0,"tau_r":120.931,"tau_r_min":1.0,"tau_r_max":1000.0,"tau_f":667.554,"tau_f_min":10.0,"tau_f_max":1000.0,"U":0.999,"U_min":0.2,"U_max":0.999,"error":11.272,"isCmOptimized":false,"isRinOptimized":false},{"Mode":"current-clamp","Erev":-8.49,"Vm":-66.17,"Rin":32.9,"Rin_min":10.0,"Rin_max":400.0,"Cm":227.96,"Cm_min":10.0,"Cm_max":400.0,"g_syn":0.46,"g_syn_min":0.1,"g_syn_max":8.0,"tau_d":15.688,"tau_d_min":1.0,"tau_d_max":30.0,"tau_r":48.416,"tau_r_min":1.0,"tau_r_max":1000.0,"tau_f":547.335,"tau_f_min":10.0,"tau_f_max":1000.0,"U":0.999,"U_min":0.2,"U_max":0.999,"error":11.272,"isCmOptimized":false,"isRinOptimized":false},{"Mode":"current-clamp","Erev":-8.49,"Vm":-66.17,"Rin":32.9,"Rin_min":10.0,"Rin_max":400.0,"Cm":227.96,"Cm_min":10.0,"Cm_max":400.0,"g_syn":0.469,"g_syn_min":0.1,"g_syn_max":8.0,"tau_d":14.809,"tau_d_min":1.0,"tau_d_max":30.0,"tau_r":561.152,"tau_r_min":1.0,"tau_r_max":1000.0,"tau_f":770.287,"tau_f_min":10.0,"tau_f_max":1000.0,"U":0.999,"U_min":0.2,"U_max":0.999,"error":11.272,"isCmOptimized":false,"isRinOptimized":false},{"Mode":"current-clamp","Erev":-8.49,"Vm":-66.17,"Rin":32.9,"Rin_min":10.0,"Rin_max":400.0,"Cm":227.96,"Cm_min":10.0,"Cm_max":400.0,"g_syn":0.466,"g_syn_min":0.1,"g_syn_max":8.0,"tau_d":15.347,"tau_d_min":1.0,"tau_d_max":30.0,"tau_r":469.891,"tau_r_min":1.0,"tau_r_max":1000.0,"tau_f":257.419,"tau_f_min":10.0,"tau_f_max":1000.0,"U":0.999,"U_min":0.2,"U_max":0.999,"error":11.272,"isCmOptimized":false,"isRinOptimized":false},{"Mode":"current-clamp","Erev":-8.49,"Vm":-66.17,"Rin":32.9,"Rin_min":10.0,"Rin_max":400.0,"Cm":227.96,"Cm_min":10.0,"Cm_max":400.0,"g_syn":0.467,"g_syn_min":0.1,"g_syn_max":8.0,"tau_d":15.218,"tau_d_min":1.0,"tau_d_max":30.0,"tau_r":564.696,"tau_r_min":1.0,"tau_r_max":1000.0,"tau_f":110.171,"tau_f_min":10.0,"tau_f_max":1000.0,"U":0.999,"U_min":0.2,"U_max":0.999,"error":11.272,"isCmOptimized":false,"isRinOptimized":false}]